{
  "name": "DVR Activity 1x3",
  "constraints": {
    "index": {
      "dVRActivity1x3": "B9A5F86F-ED62-49E9-B6D4-AE1093D02202",
      "dVRInternetTV": "6EB0A6D1-992C-4F1D-816B-83E75187FCEB",
      "guideTools": "037BB6A2-A4AF-408A-9F45-E48E0AA20E1E",
      "info": "2E48E207-00B8-481A-A57E-4FA84B51A02C"
    },
    "format": [
      "dVRActivity1x3.height ≥ 150",
      "dVRActivity1x3.width ≥ 132",
      "dVRInternetTV.height = guideTools.height",
      "dVRInternetTV.left = dVRActivity1x3.left",
      "dVRInternetTV.right = dVRActivity1x3.right",
      "dVRInternetTV.top = guideTools.bottom + 4",
      "guideTools.left = dVRActivity1x3.left",
      "guideTools.right = dVRActivity1x3.right",
      "guideTools.top = dVRActivity1x3.top",
      "info.bottom = dVRActivity1x3.bottom",
      "info.height = guideTools.height",
      "info.left = dVRActivity1x3.left",
      "info.right = dVRActivity1x3.right",
      "info.top = dVRInternetTV.bottom + 4"
    ]
  },
  "subelements": [
    {
      "uuid": "037BB6A2-A4AF-408A-9F45-E48E0AA20E1E",
      "name": "Guide / Tools",
      "shape": "rounded-rectangle",
      "style": "gloss2",
      "commands": {
        "default": {
          "class": "sendir",
          "code.index": "Dish/Dish/Guide"
        },
        "tv": {
          "class": "sendir",
          "code.index": "Samsung/Samsung%20TV/Tools"
        }
      },
      "titles": {
        "default": {
          "normal": {
            "font": "Helvetica Neue@20",
            "foreground-color": "white",
            "stroke-color": "white@50%",
            "stroke-width": -2,
            "alignment": "center",
            "text": "Guide"
          },
          "highlighted.foreground-color": "#00AFFFFF"
        },
        "tv": {
          "normal": {
            "font": "Helvetica Neue@20",
            "foreground-color": "white",
            "stroke-color": "white@50%",
            "stroke-width": -2,
            "alignment": "center",
            "text": "Tools"
          },
          "highlighted.foreground-color": "#00AFFFFF"
        }
      },
      "background-colors.default.normal": "#060606FF",
      "title-edge-insets": "{20, 20, 20, 20}"
    },
    {
      "uuid": "6EB0A6D1-992C-4F1D-816B-83E75187FCEB",
      "name": "DVR / Internet@TV",
      "shape": "rounded-rectangle",
      "style": "gloss2",
      "commands": {
        "default": {
          "class": "sendir",
          "code.index": "Dish/Dish/DVR"
        },
        "tv": {
          "class": "sendir",
          "code.index": "Samsung/Samsung%20TV/Internet@TV"
        }
      },
      "titles": {
        "default": {
          "normal": {
            "font": "Helvetica Neue@20",
            "foreground-color": "white",
            "stroke-color": "white@50%",
            "stroke-width": -2,
            "alignment": "center",
            "text": "DVR"
          },
          "highlighted.foreground-color": "#00AFFFFF"
        },
        "tv": {
          "normal": {
            "font": "Helvetica Neue@20",
            "foreground-color": "white",
            "stroke-color": "white@50%",
            "stroke-width": -2,
            "alignment": "center",
            "text": "Internet@TV"
          },
          "highlighted.foreground-color": "#00AFFFFF"
        }
      },
      "background-colors.default.normal": "#060606FF",
      "title-edge-insets": "{20, 20, 20, 20}"
    },
    {
      "uuid": "2E48E207-00B8-481A-A57E-4FA84B51A02C",
      "name": "Info",
      "shape": "rounded-rectangle",
      "style": "gloss2",
      "commands": {
        "default": {
          "class": "sendir",
          "code.index": "Dish/Dish/Info"
        },
        "tv": {
          "class": "sendir",
          "code.index": "Samsung/Samsung%20TV/Info"
        }
      },
      "titles.default": {
        "normal": {
          "font": "Helvetica Neue@20",
          "foreground-color": "white",
          "stroke-color": "white@50%",
          "stroke-width": -2,
          "alignment": "center",
          "text": "Info"
        },
        "highlighted.foreground-color": "#00AFFFFF"
      },
      "background-colors.default.normal": "#060606FF",
      "title-edge-insets": "{20, 20, 20, 20}"
    }
  ]
}