{
  "uuid": "6BAD3045-DC09-4D29-AEF3-4063D3590BDD",
  "name": "ISYDevice1",
  "unique-identifier": "uuid:00:21:b9:01:f2:b6",
  "type": "isy",
  "model-number": "1120",
  "model-name": "ISY 994i 256",
  "model-description": "X_Insteon_Lighting_Device:1",
  "manufacturer-url": "http://www.universal-devices.com",
  "manufacturer": "Universal Devices Inc.",
  "friendly-name": "ISY",
  "device-type": "urn:udi-com:device:X_Insteon_Lighting_Device:1",
  "base-url": "http://192.168.1.9",
  "nodes": [
    <@include ISYDeviceNode.json>
  ],
  "groups": [
    <@include ISYDeviceGroup.json>
  ]
}