[
    {
        "uuid": "B0EA5B35-5CF6-40E9-B302-0F164D4A7ADD",
        "name": "Home Screen",
        "elementType": "remote",
        "backgroundImage.uuid": "32734604-9B4D-4511-BC47-7367A2C3A710", // Pro Dots.png
        "constraints": {
            "index": {
                "activityButtons": "F358CB82-496C-446D-8833-D4373777D23E",
                "bottomToolbar": "B81FFF61-4F56-43C1-9E60-3C399EB31C1B",
                "homeScreen": "B0EA5B35-5CF6-40E9-B302-0F164D4A7ADD"
            },
            "format": [
                "activityButtons.centerX = homeScreen.centerX",
                "activityButtons.centerY = homeScreen.centerY - 22",
                "bottomToolbar.bottom = homeScreen.bottom",
                "bottomToolbar.left = homeScreen.left",
                "bottomToolbar.right = homeScreen.right"
            ]
        },
        "backgroundColor": "black",
        "subelements": [
            {
                "uuid": "F358CB82-496C-446D-8833-D4373777D23E",
                "name": "Activity Buttons",
                "elementType": "button-group",
                "constraints": {
                    "index": {
                        "activityButtons": "F358CB82-496C-446D-8833-D4373777D23E",
                        "appleTV": "58A7D2DB-9635-486A-9336-43D6292674BA",
                        "dish": "92E33ABD-9893-47A9-8922-86146A94C0E4",
                        "playstation": "DB1C794B-A3BB-4C9E-91EC-88A1D3FB401A",
                        "sonos": "19F3F351-AB2B-435D-A31A-ECB703DDE993"
                    },
                    "format": [
                        "activityButtons.height = activityButtons.width",
                        "activityButtons.width = 300",
                        "appleTV.centerY = activityButtons.centerY * 1.5",
                        "appleTV.centerX = activityButtons.centerX * 0.5",
                        "appleTV.width = dish.width",
                        "dish.centerX = activityButtons.centerX * 0.5",
                        "dish.centerY = activityButtons.centerY * 0.5",
                        "dish.width = activityButtons.width * 0.5",
                        "playstation.centerX = activityButtons.centerX * 1.5",
                        "playstation.centerY = activityButtons.centerY * 0.5",
                        "playstation.width = dish.width",
                        "sonos.centerX = activityButtons.centerX * 1.5",
                        "sonos.centerY = activityButtons.centerY * 1.5",
                        "sonos.width = dish.width"
                    ]
                },
                "subelements": [
                    {
                        "uuid": "92E33ABD-9893-47A9-8922-86146A94C0E4",
                        "name": "Dish",
                        "elementType": "button",
                        "shape": "rounded-rectangle",
                        "style": "gloss2",
                        "constraints": {
                            "index.dish": "92E33ABD-9893-47A9-8922-86146A94C0E4",
                            "format": "dish.height = dish.width"
                        },
                        "commands.default": {
                            "class": "activity",
                            "activity.uuid": "D6993345-F209-4CBD-A39C-C912BF550AC5"
                        },
                        "titles.default.normal": {
                            "font": "HelveticaNeue@20",
                            "foreground-color": "white",
                            "paragraph-style.alignment": "center",
                            "stroke-color": "white@50%",
                            "stroke-width": -2,
                            "text": "Dish"
                        },
                        "icons.default.colors": {
                            "highlighted": "#00AFFFFF",
                            "disabled": "#7F7F7FFF",
                            "normal": "white"
                        },
                        "backgroundColors.default.normal": "#060606FF",
                        "titleEdgeInsets": "{20, 20, 20, 20}"
                    },
                    {
                        "uuid": "DB1C794B-A3BB-4C9E-91EC-88A1D3FB401A",
                        "name": "Playstation",
                        "elementType": "button",
                        "shape": "rounded-rectangle",
                        "style": "gloss2",
                        "constraints": {
                            "index.playstation": "DB1C794B-A3BB-4C9E-91EC-88A1D3FB401A",
                            "format": "playstation.height = playstation.width"
                        },
                        "commands.default": {
                            "class": "activity",
                            "activity.uuid": "863844ED-4BCD-4B75-AD67-DEE8A23233D1"
                        },
                        "titles.default.normal": {
                            "font": "HelveticaNeue@20",
                            "foreground-color": "white",
                            "paragraph-style.alignment": "center",
                            "stroke-color": "white@50%",
                            "stroke-width": -2,
                            "text": "Playstation"
                        },
                        "icons.default.colors": {
                            "highlighted": "#00AFFFFF",
                            "disabled": "#7F7F7FFF",
                            "normal": "white"
                        },
                        "backgroundColors.default.normal": "#060606FF",
                        "titleEdgeInsets": "{20, 20, 20, 20}"
                    },
                    {
                        "uuid": "58A7D2DB-9635-486A-9336-43D6292674BA",
                        "name": "Apple TV",
                        "elementType": "button",
                        "shape": "rounded-rectangle",
                        "style": "gloss2",
                        "constraints": {
                            "index.appleTV": "58A7D2DB-9635-486A-9336-43D6292674BA",
                            "format": "appleTV.height = appleTV.width"
                        },
                        "commands.default": {
                            "class": "activity",
                            "activity.uuid": "DEB5EAC1-7040-4CA1-A309-423BACB533A4"
                        },
                        "titles.default.normal": {
                            "font": "HelveticaNeue@20",
                            "foreground-color": "white",
                            "paragraph-style.alignment": "center",
                            "stroke-color": "white@50%",
                            "stroke-width": -2,
                            "text": " TV"
                        },
                        "icons.default.colors": {
                            "highlighted": "#00AFFFFF",
                            "disabled": "#7F7F7FFF",
                            "normal": "white"
                        },
                        "backgroundColors.default.normal": "#060606FF",
                        "titleEdgeInsets": "{20, 20, 20, 20}"
                    },
                    {
                        "uuid": "19F3F351-AB2B-435D-A31A-ECB703DDE993",
                        "name": "Sonos",
                        "elementType": "button",
                        "shape": "rounded-rectangle",
                        "style": "gloss2",
                        "constraints": {
                            "index.sonos": "19F3F351-AB2B-435D-A31A-ECB703DDE993",
                            "format": "sonos.height = sonos.width"
                        },
                        "commands.default": {
                            "uuid": "E8565A0A-C72E-4C27-8093-C9FFDE2ED304",
                            "class": "activity",
                            "activity": "8C1918C0-300F-4DBF-AC09-B8DB9CF55290"
                        },
                        "titles.default.normal": {
                            "font": "HelveticaNeue@20",
                            "foreground-color": "white",
                            "paragraph-style.alignment": "center",
                            "stroke-color": "white@50%",
                            "stroke-width": -2,
                            "text": "Sonos"
                        },
                        "icons.default.colors": {
                            "highlighted": "#00AFFFFF",
                            "disabled": "#7F7F7FFF",
                            "normal": "white"
                        },
                        "backgroundColors.default.normal": "#060606FF",
                        "titleEdgeInsets": "{20, 20, 20, 20}"
                    }
                ]
            },
            {
                "uuid": "B81FFF61-4F56-43C1-9E60-3C399EB31C1B",
                "name": "Bottom Toolbar",
                "elementType": "button-group",
                "role": "toolbar",
                "shape": "rectangle",
                "constraints": {
                    "index": {
                        "bottomToolbar": "B81FFF61-4F56-43C1-9E60-3C399EB31C1B",
                        "lightsOff": "085F92D0-7D04-4586-BD2E-BCD0F0AFB729",
                        "lightsOn": "65E065E6-2976-4726-99E4-9D4D932804E4"
                    },
                    "format": [
                        "bottomToolbar.height = 44",
                        "lightsOff.bottom = bottomToolbar.bottom",
                        "lightsOff.left = lightsOn.right + 40",
                        "lightsOff.top = bottomToolbar.top",
                        "lightsOff.width = lightsOn.width",
                        "lightsOn.bottom = bottomToolbar.bottom",
                        "lightsOn.left = bottomToolbar.left + 20",
                        "lightsOn.top = bottomToolbar.top"
                    ]
                },
                "backgroundColor": "flipside",
                "subelements": [
                    {
                        "uuid": "65E065E6-2976-4726-99E4-9D4D932804E4",
                        "name": "Lights On",
                        "elementType": "button",
                        "role": "toolbar",
                        "constraints": {
                            "index.lightsOn": "65E065E6-2976-4726-99E4-9D4D932804E4",
                            "format": "lightsOn.width = 44"
                        },
                        "commands.default": {
                            "class": "http",
                            "url": "http://10.0.1.27/0?1201=I=0"
                        },
                        "icons.default": {
                            "colors": {
                                "highlighted": "#00AFFFFF",
                                "normal": "white"
                            },
                            "normal.uuid": "A3110AD7-45A7-45BE-A2B5-67F9A3953D38"
                        }
                    },
                    {
                        "uuid": "085F92D0-7D04-4586-BD2E-BCD0F0AFB729",
                        "name": "Lights Off",
                        "elementType": "button",
                        "role": "toolbar",
                        "commands.default": {
                            "class": "http",
                            "url": "http://10.0.1.27/0?1401=I=0"
                        },
                        "icons.default": {
                            "colors": {
                                "highlighted": "#00AFFFFF",
                                "normal": "#7F7F7FFF"
                            },
                            "normal.uuid": "A3110AD7-45A7-45BE-A2B5-67F9A3953D38"
                        }
                    }
                ]
            }
        ],
        "modes": [
            "default"
        ]
    },
    {
        "uuid": "F668F0D5-80E4-46A4-A703-EF5A1601C645",
        "name": "Dish Hopper Activity",
        "elementType": "remote",
        "key": "activity1",
        "backgroundImage.uuid": "32734604-9B4D-4511-BC47-7367A2C3A710", // Pro Dots.png
        "options": "top-bar-hidden",
        "constraints": {
            "index": {
                "dishHopperActivity": "F668F0D5-80E4-46A4-A703-EF5A1601C645",
                "dVRActivity1x3": "B9A5F86F-ED62-49E9-B6D4-AE1093D02202",
                "dVRActivityDPad": "B0398BDA-B312-4FD8-8CD4-2847A41F8E35",
                "dVRActivityNumberPad": "A2EFC284-8F45-45B1-9A4B-DB448A2AEAE7",
                "dVRActivityRocker": "7A847BB9-88AE-4F64-B535-FD095EE5DB83",
                "dVRActivityTransport": "D505193C-C9D5-4D89-9C9F-D0B24EAE6D69",
                "homeAndPowerButtons": "B8BEFBE3-9D3C-4DA0-9D2E-FD8EA4BBCB7D",
                "leftOverlayPanel": "7521F420-F677-44C9-97BA-4AF836779C21",
                "selectionPanel": "A6394F58-79C6-4B6C-962D-1DDD6BE1C36F"
            },
            "format": [
                "dVRActivity1x3.left = dishHopperActivity.left + 20",
                "dVRActivity1x3.top = dishHopperActivity.top + 20",
                "dVRActivityDPad.centerX = dishHopperActivity.centerX",
                "dVRActivityDPad.centerY = dishHopperActivity.centerY + 70 @750",
                "dVRActivityDPad.top = dVRActivity1x3.bottom + 20",
                "dVRActivityNumberPad.height = dishHopperActivity.height",
                "dVRActivityNumberPad.left = dishHopperActivity.left",
                "dVRActivityNumberPad.right = dishHopperActivity.right",
                "dVRActivityNumberPad.top = dishHopperActivity.top @998",
                "dVRActivityRocker.height = dVRActivity1x3.height",
                "dVRActivityRocker.right = dishHopperActivity.right - 20",
                "dVRActivityRocker.top = dishHopperActivity.top + 20",
                "dVRActivityTransport.bottom = dishHopperActivity.bottom @998",
                "dVRActivityTransport.left = dishHopperActivity.left",
                "dVRActivityTransport.right = dishHopperActivity.right",
                "homeAndPowerButtons.bottom = dishHopperActivity.bottom - 20",
                "homeAndPowerButtons.centerX = dishHopperActivity.centerX",
                "leftOverlayPanel.bottom = dishHopperActivity.bottom",
                "leftOverlayPanel.left = dishHopperActivity.left @998",
                "leftOverlayPanel.top = dishHopperActivity.top",
                "selectionPanel.centerY = dishHopperActivity.centerY",
                "selectionPanel.right = dishHopperActivity.right @998"
            ]
        },
        "backgroundColor": "black",
        "subelements": [
            {
                "uuid": "B9A5F86F-ED62-49E9-B6D4-AE1093D02202",
                "name": "DVR Activity 1x3",
                "elementType": "button-group",
                "constraints": {
                    "index": {
                        "dVRActivity1x3": "B9A5F86F-ED62-49E9-B6D4-AE1093D02202",
                        "dVRInternetTV": "6EB0A6D1-992C-4F1D-816B-83E75187FCEB",
                        "guideTools": "037BB6A2-A4AF-408A-9F45-E48E0AA20E1E",
                        "info": "2E48E207-00B8-481A-A57E-4FA84B51A02C"
                    },
                    "format": [
                        "dVRActivity1x3.height ≥ 150",
                        "dVRActivity1x3.width ≥ 132",
                        "dVRInternetTV.height = guideTools.height",
                        "dVRInternetTV.left = dVRActivity1x3.left",
                        "dVRInternetTV.right = dVRActivity1x3.right",
                        "dVRInternetTV.top = guideTools.bottom + 4",
                        "guideTools.left = dVRActivity1x3.left",
                        "guideTools.right = dVRActivity1x3.right",
                        "guideTools.top = dVRActivity1x3.top",
                        "info.bottom = dVRActivity1x3.bottom",
                        "info.height = guideTools.height",
                        "info.left = dVRActivity1x3.left",
                        "info.right = dVRActivity1x3.right",
                        "info.top = dVRInternetTV.bottom + 4"
                    ]
                },
                "subelements": [
                    {
                        "uuid": "037BB6A2-A4AF-408A-9F45-E48E0AA20E1E",
                        "name": "Guide / Tools",
                        "elementType": "button",
                        "shape": "rounded-rectangle",
                        "style": "gloss2",
                        "commands": {
                            "default": {
                                "class": "sendir",
                                "code.uuid": "CC3DAB57-1897-44CB-AA05-6B48CBE96A6D"
                            },
                            "tv": {
                                "class": "sendir",
                                "code.uuid": "A32C02D7-6CE0-46C0-8469-8F074C6D96E5"
                            }
                        },
                        "titles": {
                            "default.normal": {
                                "font": "HelveticaNeue@20",
                                "foreground-color": "white",
                                "stroke-color": "white@50%",
                                "stroke-width": -2,
                                "paragraph-style.alignment": "center",
                                "text": "Guide"
                            },
                            "tv.normal": {
                                "font": "HelveticaNeue@20",
                                "foreground-color": "white",
                                "stroke-color": "white@50%",
                                "stroke-width": -2,
                                "paragraph-style.alignment": "center",
                                "text": "Tools"
                            }
                        },
                        "backgroundColors.default.normal": "#060606FF",
                        "titleEdgeInsets": "{20, 20, 20, 20}"
                    },
                    {
                        "uuid": "6EB0A6D1-992C-4F1D-816B-83E75187FCEB",
                        "name": "DVR / Internet@TV",
                        "elementType": "button",
                        "shape": "rounded-rectangle",
                        "style": "gloss2",
                        "commands": {
                            "default": {
                                "class": "sendir",
                                "code.uuid": "A4A417A0-F5AA-45E4-839E-F0727EC81A3F"
                            },
                            "tv": {
                                "class": "sendir",
                                "code.uuid": "31E6CBAC-BA05-42DD-827D-45496EBDC78B"
                            }
                        },
                        "titles": {
                            "default.normal": {
                                "font": "HelveticaNeue@20",
                                "foreground-color": "white",
                                "stroke-color": "white@50%",
                                "stroke-width": -2,
                                "paragraph-style.alignment": "center",
                                "text": "DVR"
                            },
                            "tv.normal": {
                                "font": "HelveticaNeue@20",
                                "foreground-color": "white",
                                "stroke-color": "white@50%",
                                "stroke-width": -2,
                                "paragraph-style.alignment": "center",
                                "text": "Internet@TV"
                            }
                        },
                        "backgroundColors.default.normal": "#060606FF",
                        "titleEdgeInsets": "{20, 20, 20, 20}"
                    },
                    {
                        "uuid": "2E48E207-00B8-481A-A57E-4FA84B51A02C",
                        "name": "Info",
                        "elementType": "button",
                        "shape": "rounded-rectangle",
                        "style": "gloss2",
                        "commands": {
                            "default": {
                                "class": "sendir",
                                "code.uuid": "456D6184-88CF-473C-BF42-16ABF13D1F10"
                            },
                            "tv": {
                                "class": "sendir",
                                "code.uuid": "30B1392A-7827-48AB-81DE-CA17439BC738"
                            }
                        },
                        "titles.default.normal": {
                            "font": "HelveticaNeue@20",
                            "foreground-color": "white",
                            "stroke-color": "white@50%",
                            "stroke-width": -2,
                            "paragraph-style.alignment": "center",
                            "text": "Info"
                        },
                        "backgroundColors.default.normal": "#060606FF",
                        "titleEdgeInsets": "{20, 20, 20, 20}"
                    }
                ]
            },
            {
                "uuid": "7A847BB9-88AE-4F64-B535-FD095EE5DB83",
                "name": "DVR Activity Rocker",
                "elementType": "button-group",
                "role": "rocker",
                "command-set-collection.default": {
                    "CH": {
                        "type": "rocker",
                        "top": {
                            "class": "sendir",
                            "code.uuid": "11B0541B-5C94-49A0-853A-D8C94A76998B"
                        },
                        "bottom": {
                            "class": "sendir",
                            "code.uuid": "034EC537-9817-45BE-A66E-E58C7EC3AEF9"
                        }
                    },
                    "PAGE": {
                        "type": "rocker",
                        "top": {
                            "class": "sendir",
                            "code.uuid": "8F9E00ED-FAFA-40B3-A1FA-01B0DF073A75"
                        },
                        "bottom": {
                            "class": "sendir",
                            "code.uuid": "8A77DAEA-8B71-4525-917F-916AA636AEBA"
                        }
                    },
                    "VOL": {
                        "type": "rocker",
                        "top": {
                            "class": "sendir",
                            "code.uuid": "DFBB376D-E061-448C-922C-32B20F69D11C"
                        },
                        "bottom": {
                            "class": "sendir",
                            "code.uuid": "C27992CE-912E-4D75-8938-AE80A0C2F9F0"
                        }
                    }
                },
                "shape": "rounded-rectangle",
                "style": "border gloss1",
                "constraints": {
                    "index": {
                        "buttonBottom": "A947EAE0-0FFE-4448-8269-76F8954DF865",
                        "buttonTop": "91C3F776-6FB3-438F-9657-758A007CC23E",
                        "dVRActivityRocker": "7A847BB9-88AE-4F64-B535-FD095EE5DB83"
                    },
                    "format": [
                        "buttonBottom.height = buttonTop.height",
                        "buttonBottom.left = dVRActivityRocker.left",
                        "buttonBottom.right = dVRActivityRocker.right",
                        "buttonBottom.top = buttonTop.bottom",
                        "buttonTop.height = dVRActivityRocker.height * 0.5",
                        "buttonTop.left = dVRActivityRocker.left",
                        "buttonTop.right = dVRActivityRocker.right",
                        "buttonTop.top = dVRActivityRocker.top",
                        "dVRActivityRocker.height ≥ 150",
                        "dVRActivityRocker.width = 70"
                    ]
                },
                "subelements": [
                    {
                        "uuid": "91C3F776-6FB3-438F-9657-758A007CC23E",
                        "name": "Button Top",
                        "elementType": "button",
                        "role": "rocker-top",
                        "icons.default": {
                            "colors": {
                                "highlighted": "#00AFFFFF",
                                "disabled": "#7F7F7FFF",
                                "normal": "white"
                            },
                            "normal.uuid": "A4462840-4238-4F3F-9C5F-CA4BEBBF1516" // 709-plus.png
                        }
                    },
                    {
                        "uuid": "A947EAE0-0FFE-4448-8269-76F8954DF865",
                        "name": "Button Bottom",
                        "elementType": "button",
                        "role": "rocker-bottom",
                        "icons.default": {
                            "colors": {
                                "highlighted": "#00AFFFFF",
                                "disabled": "#7F7F7FFF",
                                "normal": "white"
                            },
                            "normal.uuid": "EC43A955-CEB8-4331-AC89-C071F71346E9" // 901-minus.png
                        }
                    }
                ],
                "labelConstraints": "H:|[label] V:|[label]"
            },
            {
                "uuid": "B0398BDA-B312-4FD8-8CD4-2847A41F8E35",
                "name": "DVR Activity DPad",
                "elementType": "button-group",
                "role": "dpad",
                "shape": "oval",
                "style": "gloss2",
                "command-set.default": {
                    "type": "dpad",
                    "up": {
                        "class": "sendir",
                        "code.uuid": "1C8D165D-4BCD-4CC7-B89F-8FAF9047B0A5"
                    },
                    "down": {
                        "class": "sendir",
                        "code.uuid": "EE477ADE-805D-46BF-958E-711561A0E621"
                    },
                    "left": {
                        "class": "sendir",
                        "code.uuid": "7CB204B0-2837-4612-BF3D-6638D8B3D93B"
                    },
                    "right": {
                        "class": "sendir",
                        "code.uuid": "0BBC99B9-E435-490E-ACE7-DF53DDD4E2F7"
                    },
                    "center": {
                        "class": "sendir",
                        "code.uuid": "E551D890-CFC0-4000-BE8C-06873C8AECDB"
                    }
                },
                "constraints": {
                    "index": {
                        "buttonCenter": "83B25E99-F70E-45DF-9831-FCBE2C34F6ED",
                        "buttonDown": "9A4F22FD-A164-4278-BB62-C757E2DE35B1",
                        "buttonLeft": "5B3195B3-64BA-44BD-A233-52A6C35BBF91",
                        "buttonRight": "4DC81EAD-9EAA-4AD6-8F36-58149CCB737D",
                        "buttonUp": "DAAF0866-265A-41C8-AA68-CAFF633E1190",
                        "dVRActivityDPad": "B0398BDA-B312-4FD8-8CD4-2847A41F8E35"
                    },
                    "format": [
                        "buttonCenter.centerX = dVRActivityDPad.centerX",
                        "buttonCenter.centerY = dVRActivityDPad.centerY",
                        "buttonCenter.width = dVRActivityDPad.width * 0.3",
                        "buttonDown.bottom = dVRActivityDPad.bottom",
                        "buttonDown.left = buttonLeft.right",
                        "buttonDown.right = buttonRight.left",
                        "buttonDown.top = buttonCenter.bottom",
                        "buttonLeft.bottom = buttonDown.top",
                        "buttonLeft.left = dVRActivityDPad.left",
                        "buttonLeft.right = buttonCenter.left",
                        "buttonLeft.top = buttonUp.bottom",
                        "buttonRight.bottom = buttonDown.top",
                        "buttonRight.left = buttonCenter.right",
                        "buttonRight.right = dVRActivityDPad.right",
                        "buttonRight.top = buttonUp.bottom",
                        "buttonUp.bottom = buttonCenter.top",
                        "buttonUp.left = buttonLeft.right",
                        "buttonUp.right = buttonRight.left",
                        "buttonUp.top = dVRActivityDPad.top",
                        "dVRActivityDPad.height = 280",
                        "dVRActivityDPad.width = dVRActivityDPad.height"
                    ]
                },
                "backgroundColor": "black",
                "subelements": [
                    {
                        "uuid": "83B25E99-F70E-45DF-9831-FCBE2C34F6ED",
                        "name": "Button Center",
                        "elementType": "button",
                        "role": "dpad-center",
                        "titles.default": {
                            "normal": {
                                "font": "HelveticaNeue@28",
                                "foreground-color": "white",
                                "stroke-color": "white@50%",
                                "stroke-width": -2,
                                "text": "OK"
                            },
                            "highlighted": {
                                "font": "HelveticaNeue@28",
                                "foreground-color": "#00AFFFFF",
                                "stroke-color": "#00AFFFFF@50%",
                                "stroke-width": -2,
                                "text": "OK"
                            }
                        },
                        "constraints": {
                            "index.buttonCenter": "83B25E99-F70E-45DF-9831-FCBE2C34F6ED",
                            "format": [
                                "buttonCenter.height = buttonCenter.width"
                            ]
                        },
                        "titleEdgeInsets": "{20, 20, 20, 20}"
                    },
                    {
                        "uuid": "DAAF0866-265A-41C8-AA68-CAFF633E1190",
                        "name": "Button Up",
                        "elementType": "button",
                        "role": "dpad-up",
                        "icons.default": {
                            "colors": {
                                "highlighted": "#00AFFFFF",
                                "disabled": "#7F7F7FFF",
                                "normal": "white"
                            },
                            "normal.uuid": "915A2613-9056-464D-8D89-5777CD05B7D8" // 763-arrow-up.png
                        }
                    },
                    {
                        "uuid": "9A4F22FD-A164-4278-BB62-C757E2DE35B1",
                        "name": "Button Down",
                        "elementType": "button",
                        "role": "dpad-down",
                        "icons.default": {
                            "colors": {
                                "highlighted": "#00AFFFFF",
                                "disabled": "#7F7F7FFF",
                                "normal": "white"
                            },
                            "normal.uuid": "03A0DB5D-2091-4896-BC7F-E4067373C8B4" // 764-arrow-down.png
                        }
                    },
                    {
                        "uuid": "5B3195B3-64BA-44BD-A233-52A6C35BBF91",
                        "name": "Button Left",
                        "elementType": "button",
                        "role": "dpad-left",
                        "icons.default": {
                            "colors": {
                                "highlighted": "#00AFFFFF",
                                "disabled": "#7F7F7FFF",
                                "normal": "white"
                            },
                            "normal.uuid": "7D376411-412E-43E3-BB70-FB5ECD73C5E4" // 765-arrow-left.png
                        }
                    },
                    {
                        "uuid": "4DC81EAD-9EAA-4AD6-8F36-58149CCB737D",
                        "name": "Button Right",
                        "elementType": "button",
                        "role": "dpad-right",
                        "icons.default": {
                            "colors": {
                                "highlighted": "#00AFFFFF",
                                "disabled": "#7F7F7FFF",
                                "normal": "white"
                            },
                            "normal.uuid": "7483F603-A928-4E61-8042-41A82F8424EA" // 766-arrow-right.png
                        }
                    }
                ]
            },
            {
                "uuid": "B8BEFBE3-9D3C-4DA0-9D2E-FD8EA4BBCB7D",
                "name": "Home and Power Buttons",
                "elementType": "button-group",
                "constraints": {
                    "index": {
                        "homeAndPowerButtons": "B8BEFBE3-9D3C-4DA0-9D2E-FD8EA4BBCB7D",
                        "homeButton": "8FD73238-A965-40D3-954E-1E486D5964F7",
                        "powerOffAndExitActivity": "A60C6C80-513A-47EC-A720-0D9A28E18D94"
                    },
                    "format": [
                        "homeAndPowerButtons.height = 50",
                        "homeAndPowerButtons.width = 300",
                        "homeButton.centerY = homeAndPowerButtons.centerY",
                        "homeButton.left = homeAndPowerButtons.left",
                        "powerOffAndExitActivity.centerY = homeAndPowerButtons.centerY",
                        "powerOffAndExitActivity.right = homeAndPowerButtons.right"
                    ]
                },
                "subelements": [
                    {
                        "uuid": "8FD73238-A965-40D3-954E-1E486D5964F7",
                        "name": "Home Button",
                        "elementType": "button",
                        "shape": "oval",
                        "style": "gloss1",
                        "command.default": {
                            "class": "switch",
                            "type": "remote",
                            "target": "B0EA5B35-5CF6-40E9-B302-0F164D4A7ADD"
                        },
                        "constraints": {
                            "index.homeButton": "8FD73238-A965-40D3-954E-1E486D5964F7",
                            "format": [
                                "homeButton.height = homeButton.width",
                                "homeButton.width = 50"
                            ]
                        },
                        "icons.default": {
                            "colors": {
                                "highlighted": "#00AFFFFF",
                                "disabled": "#7F7F7FFF",
                                "normal": "white"
                            },
                            "normal.uuid": "DC256402-D8A9-461A-A158-F60D0EF63EF7" // 502-house.png
                        },
                        "backgroundColors.default.normal": "#060606FF"
                    },
                    {
                        "uuid": "A60C6C80-513A-47EC-A720-0D9A28E18D94",
                        "name": "Power Off and Exit Activity",
                        "elementType": "button",
                        "key": "activity1",
                        "shape": "oval",
                        "style": "gloss1",
                        "command.default": {
                            "class": "activity",
                            "activity.uuid": "D6993345-F209-4CBD-A39C-C912BF550AC5"
                        },
                        "constraints": {
                            "index.powerOffAndExitActivity": "A60C6C80-513A-47EC-A720-0D9A28E18D94",
                            "format": [
                                "powerOffAndExitActivity.height = powerOffAndExitActivity.width",
                                "powerOffAndExitActivity.width = 50"
                            ]
                        },
                        "icons.default": {
                            "colors": {
                                "highlighted": "#00AFFFFF",
                                "disabled": "#7F7F7FFF",
                                "normal": "white"
                            },
                            "normal.uuid": "0EA0C544-F7A7-4D69-BCB2-C3E6E8346BB8" // 51-power.png
                        },
                        "backgroundColors.default.normal": "#060606FF"
                    }
                ]
            },
            {
                "uuid": "A2EFC284-8F45-45B1-9A4B-DB448A2AEAE7",
                "name": "DVR Activity Number Pad",
                "elementType": "button-group",
                "role": "numberpad",
                "subtype": "top1",
                "command-set.default": {
                    "type": "numberpad",
                    "1": {
                        "class": "sendir",
                        "code.uuid": "0313E4A0-996F-4968-8DAB-0C799BD4D2A6"
                    },
                    "2": {
                        "class": "sendir",
                        "code.uuid": "1B86BE5A-F8D6-4798-895A-B881E6E623D1"
                    },
                    "3": {
                        "class": "sendir",
                        "code.uuid": "266FC2EF-2EDB-4A41-A42D-2BC1129DFECA"
                    },
                    "4": {
                        "class": "sendir",
                        "code.uuid": "4D24C204-E3FC-4473-A438-38E5B6EE3FE6"
                    },
                    "5": {
                        "class": "sendir",
                        "code.uuid": "40BCAC68-BC65-4AD4-A5F9-39A541AEF71E"
                    },
                    "6": {
                        "class": "sendir",
                        "code.uuid": "E57C7D62-3597-45B0-9B80-45F5559F7C18"
                    },
                    "7": {
                        "class": "sendir",
                        "code.uuid": "B9007475-33AA-4CD7-87E7-3EEF413486FD"
                    },
                    "8": {
                        "class": "sendir",
                        "code.uuid": "E6195194-F7FE-42C2-962A-13A6AA6858E0"
                    },
                    "9": {
                        "class": "sendir",
                        "code.uuid": "019887BD-C57E-4CBD-A8C0-62C1167601D9"
                    },
                    "0": {
                        "class": "sendir",
                        "code.uuid": "4D359D0D-BBE0-4BF5-85D3-9BF2CD338563"
                    },
                    "aux1": {
                        "class": "sendir",
                        "code.uuid": "60500AB6-9450-4BEA-86AD-CDB74E90A768"
                    },
                    "aux2": {
                        "class": "sendir",
                        "code.uuid": "E551D890-CFC0-4000-BE8C-06873C8AECDB"
                    }
                },
                "constraints": {
                    "index": {
                        "button0": "07B126DA-A7BE-4B1C-ACD1-5DD5F551DDF7",
                        "button1": "4A9A5126-CCDD-4282-9D6E-581EB1A7768D",
                        "button2": "FD25B8D7-B6A3-46F5-A14D-BA66EC9B6624",
                        "button3": "26D4A4EA-AD0A-4A4F-8F19-AD2EBDF2B4DD",
                        "button4": "F7E72BB6-7C56-4D71-8B09-4FE29EF76EB6",
                        "button5": "FD56CF91-26C4-47A2-9052-7D3504C85F59",
                        "button6": "A9A11EB5-341F-42BB-A482-D81EED4D6436",
                        "button7": "8C750F21-4D8D-4F5A-8E1B-0B9294AF2A7C",
                        "button8": "789737C2-D0D7-401B-B079-D305C65DA5F9",
                        "button9": "2F310C3B-37A8-4AE0-B652-21160A3DBB00",
                        "buttonAux1": "6F2F49AE-EC61-404B-A544-468A8D9EB74A",
                        "buttonAux2": "D7E718BE-7E0D-4C19-8A75-625C8C5445A1",
                        "dVRActivityNumberPad": "A2EFC284-8F45-45B1-9A4B-DB448A2AEAE7",
                        "tuck": "E9D65885-43D4-4DFA-A3A6-C4ADCF70D94A"
                    },
                    "format": [
                        "button1.left = dVRActivityNumberPad.left",
                        "button1.top = dVRActivityNumberPad.top",
                        "button1.bottom = button2.bottom",
                        "button2.left = button1.right",
                        "button2.top = dVRActivityNumberPad.top",
                        "button2.width = button1.width",
                        "button3.left = button2.right",
                        "button3.right = dVRActivityNumberPad.right",
                        "button3.top = dVRActivityNumberPad.top",
                        "button3.bottom = button2.bottom",
                        "button3.width = button1.width",
                        "button4.left = dVRActivityNumberPad.left",
                        "button4.top = button1.bottom",
                        "button4.right = button1.right",
                        "button4.bottom = button5.bottom",
                        "button5.left = button2.left",
                        "button5.top = button2.bottom",
                        "button5.right = button2.right",
                        "button5.height = button2.height",
                        "button6.left = button3.left",
                        "button6.right = dVRActivityNumberPad.right",
                        "button6.top = button3.bottom",
                        "button6.bottom = button5.bottom",
                        "button7.left = dVRActivityNumberPad.left",
                        "button7.top = button4.bottom",
                        "button7.right = button4.right",
                        "button7.bottom = button8.bottom",
                        "button8.left = button5.left",
                        "button8.top = button5.bottom",
                        "button8.right = button5.right",
                        "button8.height = button2.height",
                        "button9.left = button6.left",
                        "button9.right = button6.right",
                        "button9.top = button6.bottom",
                        "button9.bottom = button8.bottom",
                        "buttonAux1.left = dVRActivityNumberPad.left",
                        "buttonAux1.top = button7.bottom",
                        "buttonAux1.bottom = button0.bottom",
                        "buttonAux1.right = button7.right",
                        "button0.left = button8.left",
                        "button0.top = button8.bottom",
                        "button0.right = button8.right",
                        "button0.bottom = tuck.top",
                        "button0.height = button2.height",
                        "buttonAux2.left = button9.left",
                        "buttonAux2.right = dVRActivityNumberPad.right",
                        "buttonAux2.top = button9.bottom",
                        "buttonAux2.bottom = button0.bottom",
                        "tuck.left = dVRActivityNumberPad.left",
                        "tuck.right = dVRActivityNumberPad.right",
                        "tuck.bottom = dVRActivityNumberPad.bottom",
                        "tuck.height = button2.height"
                    ]
                },
                "backgroundColor": "white@75%",
                "subelements": [
                    {
                        "uuid": "4A9A5126-CCDD-4282-9D6E-581EB1A7768D",
                        "name": "Button 1",
                        "elementType": "button",
                        "role": "numberpad-1",
                        "state": "disabled",
                        "shape": "rounded-rectangle",
                        "style": "gloss2",
                        "titles.default.normal": {
                            "font": "HelveticaNeue@20",
                            "foreground-color": "white",
                            "stroke-color": "white@50%",
                            "stroke-width": -2,
                            "text": "1"
                        },
                        "backgroundColors.default.normal": "#060606FF",
                        "titleEdgeInsets": "{20, 20, 20, 20}"
                    },
                    {
                        "uuid": "FD25B8D7-B6A3-46F5-A14D-BA66EC9B6624",
                        "name": "Button 2",
                        "elementType": "button",
                        "role": "numberpad-2",
                        "state": "disabled",
                        "shape": "rounded-rectangle",
                        "style": "gloss2",
                        "titles.default.normal": {
                            "font": "HelveticaNeue@20",
                            "foreground-color": "white",
                            "stroke-color": "white@50%",
                            "stroke-width": -2,
                            "text": "2"
                        },
                        "backgroundColors.default.normal": "#060606FF",
                        "titleEdgeInsets": "{20, 20, 20, 20}"
                    },
                    {
                        "uuid": "26D4A4EA-AD0A-4A4F-8F19-AD2EBDF2B4DD",
                        "name": "Button 3",
                        "elementType": "button",
                        "role": "numberpad-3",
                        "state": "disabled",
                        "shape": "rounded-rectangle",
                        "style": "gloss2",
                        "titles.default.normal": {
                            "font": "HelveticaNeue@20",
                            "foreground-color": "white",
                            "stroke-color": "white@50%",
                            "stroke-width": -2,
                            "text": "3"
                        },
                        "backgroundColors.default.normal": "#060606FF",
                        "titleEdgeInsets": "{20, 20, 20, 20}"
                    },
                    {
                        "uuid": "F7E72BB6-7C56-4D71-8B09-4FE29EF76EB6",
                        "name": "Button 4",
                        "elementType": "button",
                        "role": "numberpad-4",
                        "state": "disabled",
                        "shape": "rounded-rectangle",
                        "style": "gloss2",
                        "titles.default.normal": {
                            "font": "HelveticaNeue@20",
                            "foreground-color": "white",
                            "stroke-color": "white@50%",
                            "stroke-width": -2,
                            "text": "4"
                        },
                        "backgroundColors.default.normal": "#060606FF",
                        "titleEdgeInsets": "{20, 20, 20, 20}"
                    },
                    {
                        "uuid": "FD56CF91-26C4-47A2-9052-7D3504C85F59",
                        "name": "Button 5",
                        "elementType": "button",
                        "role": "numberpad-5",
                        "state": "disabled",
                        "shape": "rounded-rectangle",
                        "style": "gloss2",
                        "titles.default.normal": {
                            "font": "HelveticaNeue@20",
                            "foreground-color": "white",
                            "stroke-color": "white@50%",
                            "stroke-width": -2,
                            "text": "5"
                        },
                        "backgroundColors.default.normal": "#060606FF",
                        "titleEdgeInsets": "{20, 20, 20, 20}"
                    },
                    {
                        "uuid": "A9A11EB5-341F-42BB-A482-D81EED4D6436",
                        "name": "Button 6",
                        "elementType": "button",
                        "role": "numberpad-6",
                        "state": "disabled",
                        "shape": "rounded-rectangle",
                        "style": "gloss2",
                        "titles.default.normal": {
                            "font": "HelveticaNeue@20",
                            "foreground-color": "white",
                            "stroke-color": "white@50%",
                            "stroke-width": -2,
                            "text": "6"
                        },
                        "backgroundColors.default.normal": "#060606FF",
                        "titleEdgeInsets": "{20, 20, 20, 20}"
                    },
                    {
                        "uuid": "8C750F21-4D8D-4F5A-8E1B-0B9294AF2A7C",
                        "name": "Button 7",
                        "elementType": "button",
                        "role": "numberpad-7",
                        "state": "disabled",
                        "shape": "rounded-rectangle",
                        "style": "gloss2",
                        "titles.default.normal": {
                            "font": "HelveticaNeue@20",
                            "foreground-color": "white",
                            "stroke-color": "white@50%",
                            "stroke-width": -2,
                            "text": "7"
                        },
                        "backgroundColors.default.normal": "#060606FF",
                        "titleEdgeInsets": "{20, 20, 20, 20}"
                    },
                    {
                        "uuid": "789737C2-D0D7-401B-B079-D305C65DA5F9",
                        "name": "Button 8",
                        "elementType": "button",
                        "role": "numberpad-8",
                        "state": "disabled",
                        "shape": "rounded-rectangle",
                        "style": "gloss2",
                        "titles.default.normal": {
                            "font": "HelveticaNeue@20",
                            "foreground-color": "white",
                            "stroke-color": "white@50%",
                            "stroke-width": -2,
                            "text": "8"
                        },
                        "backgroundColors.default.normal": "#060606FF",
                        "titleEdgeInsets": "{20, 20, 20, 20}"
                    },
                    {
                        "uuid": "2F310C3B-37A8-4AE0-B652-21160A3DBB00",
                        "name": "Button 9",
                        "elementType": "button",
                        "role": "numberpad-9",
                        "state": "disabled",
                        "shape": "rounded-rectangle",
                        "style": "gloss2",
                        "titles.default.normal": {
                            "font": "HelveticaNeue@20",
                            "foreground-color": "white",
                            "stroke-color": "white@50%",
                            "stroke-width": -2,
                            "text": "9"
                        },
                        "backgroundColors.default.normal": "#060606FF",
                        "titleEdgeInsets": "{20, 20, 20, 20}"
                    },
                    {
                        "uuid": "07B126DA-A7BE-4B1C-ACD1-5DD5F551DDF7",
                        "name": "Button 0",
                        "elementType": "button",
                        "role": "numberpad-0",
                        "state": "disabled",
                        "shape": "rounded-rectangle",
                        "style": "gloss2",
                        "titles.default.normal": {
                            "font": "HelveticaNeue@20",
                            "foreground-color": "white",
                            "stroke-color": "white@50%",
                            "stroke-width": -2,
                            "text": "0"
                        },
                        "backgroundColors.default.normal": "#060606FF",
                        "titleEdgeInsets": "{20, 20, 20, 20}"
                    },
                    {
                        "uuid": "6F2F49AE-EC61-404B-A544-468A8D9EB74A",
                        "name": "Button Aux 1",
                        "elementType": "button",
                        "role": "numberpad-aux1",
                        "state": "disabled",
                        "shape": "rounded-rectangle",
                        "style": "gloss2",
                        "titles.default.normal": {
                            "font": "HelveticaNeue@20",
                            "foreground-color": "white",
                            "stroke-color": "white@50%",
                            "stroke-width": -2,
                            "text": "Exit"
                        },
                        "backgroundColors.default.normal": "#060606FF",
                        "titleEdgeInsets": "{20, 20, 20, 20}"
                    },
                    {
                        "uuid": "D7E718BE-7E0D-4C19-8A75-625C8C5445A1",
                        "name": "Button Aux 2",
                        "elementType": "button",
                        "role": "numberpad-aux2",
                        "state": "disabled",
                        "shape": "rounded-rectangle",
                        "style": "gloss2",
                        "titles.default.normal": {
                            "font": "HelveticaNeue@20",
                            "foreground-color": "white",
                            "stroke-color": "white@50%",
                            "stroke-width": -2,
                            "text": "Enter"
                        },
                        "backgroundColors.default.normal": "#060606FF",
                        "titleEdgeInsets": "{20, 20, 20, 20}"
                    },
                    {
                        "uuid": "E9D65885-43D4-4DFA-A3A6-C4ADCF70D94A",
                        "name": "Tuck",
                        "elementType": "button",
                        "role": "tuck",
                        "state": "disabled",
                        "shape": "rounded-rectangle",
                        "style": "gloss2",
                        "titles.default.normal": {
                            "font": "HelveticaNeue@20",
                            "foreground-color": "white",
                            "stroke-color": "white@50%",
                            "stroke-width": -2,
                            "text-effect": "letter-press",
                            "text": "▲"
                        },
                        "backgroundColors.default.normal": "#060606FF",
                        "titleEdgeInsets": "{20, 20, 20, 20}"
                    }
                ]
            },
            {
                "uuid": "D505193C-C9D5-4D89-9C9F-D0B24EAE6D69",
                "name": "DVR Activity Transport",
                "elementType": "button-group",
                "role": "transport",
                "subtype": "bottom1",
                "command-set.default": {
                    "type": "transport",
                    "record": {
                        "class": "sendir",
                        "code.uuid": "C613F7A8-5089-4440-B427-C121165DE70C"
                    },
                    "play": {
                        "class": "sendir",
                        "code.uuid": "7EE63EAB-1054-4DF7-A66B-9E51816AB8D0"
                    },
                    "pause": {
                        "class": "sendir",
                        "code.uuid": "5AA092F8-2D93-437F-B3D0-4006E52DC371"
                    },
                    "stop": {
                        "class": "sendir",
                        "code.uuid": "4376CED6-A57A-4930-B3A7-1A234B86291D"
                    },
                    "skip": {
                        "class": "sendir",
                        "code.uuid": "4DDE9552-4EE5-492E-98F4-8EF6600CED85"
                    },
                    "replay": {
                        "class": "sendir",
                        "code.uuid": "FEA29DF1-DA83-4775-9C73-85291A51961C"
                    },
                    "rewind": {
                        "class": "sendir",
                        "code.uuid": "3A8A1370-8842-42C7-9FB3-F01BDCCA9475"
                    },
                    "fast-forward": {
                        "class": "sendir",
                        "code.uuid": "502E0C1F-9524-4271-893C-089A45FF4BCF"
                    }
                },
                "constraints": {
                    "index": {
                        "buttonFastForward": "804894ED-2BA4-467D-A7E2-43E45ECC946B",
                        "buttonPause": "7754F230-C17E-4333-AD7F-202A34AB71E1",
                        "buttonPlay": "DF2C7FAF-D979-427E-8626-2411E79F59F1",
                        "buttonRecord": "FC1F0B10-D228-48E5-940E-997D6DD3ED67",
                        "buttonReplay": "4BD189E1-996D-4667-B1C0-80C43BC27445",
                        "buttonRewind": "D4F04A8A-C2CA-4235-8C6E-080AD7DA5A3B",
                        "buttonSkip": "08FF87FF-685F-4A56-A40C-BF954852152B",
                        "buttonStop": "5996C324-C978-4AE8-97BA-4F5468CCDEFB",
                        "dVRActivityTransport": "D505193C-C9D5-4D89-9C9F-D0B24EAE6D69",
                        "tuck": "051E7613-FE45-47CE-AE8A-F50B776348AC"
                    },
                    "format": [
                        "buttonFastForward.bottom = buttonPause.bottom",
                        "buttonFastForward.left = buttonStop.left",
                        "buttonFastForward.right = dVRActivityTransport.right",
                        "buttonFastForward.top = buttonStop.bottom",
                        "buttonPause.height = buttonPlay.height",
                        "buttonPause.left = buttonPlay.left",
                        "buttonPause.right = buttonPlay.right",
                        "buttonPause.top = buttonPlay.bottom",
                        "buttonPlay.bottom = buttonRecord.bottom",
                        "buttonPlay.left = buttonRecord.right",
                        "buttonPlay.top = dVRActivityTransport.top",
                        "buttonPlay.width = buttonRecord.width",
                        "buttonRecord.left = dVRActivityTransport.left",
                        "buttonRecord.top = dVRActivityTransport.top",
                        "buttonReplay.bottom = dVRActivityTransport.bottom",
                        "buttonReplay.left = dVRActivityTransport.left",
                        "buttonReplay.right = buttonRewind.right",
                        "buttonReplay.top = buttonRewind.bottom",
                        "buttonRewind.bottom = buttonPause.bottom",
                        "buttonRewind.left = dVRActivityTransport.left",
                        "buttonRewind.right = buttonRecord.right",
                        "buttonRewind.top = buttonRecord.bottom",
                        "buttonSkip.bottom = dVRActivityTransport.bottom",
                        "buttonSkip.left = buttonFastForward.left",
                        "buttonSkip.right = dVRActivityTransport.right",
                        "buttonSkip.top = buttonFastForward.bottom",
                        "buttonStop.bottom = buttonPlay.bottom",
                        "buttonStop.left = buttonPlay.right",
                        "buttonStop.right = dVRActivityTransport.right",
                        "buttonStop.top = dVRActivityTransport.top",
                        "buttonStop.width = buttonRecord.width",
                        "dVRActivityTransport.height = dVRActivityTransport.width",
                        "tuck.bottom = dVRActivityTransport.bottom",
                        "tuck.height = buttonPlay.height",
                        "tuck.left = buttonPause.left",
                        "tuck.right = buttonPause.right",
                        "tuck.top = buttonPause.bottom"
                    ]
                },
                "backgroundColor": "white@75%",
                "subelements": [
                    {
                        "uuid": "DF2C7FAF-D979-427E-8626-2411E79F59F1",
                        "name": "Button Play",
                        "elementType": "button",
                        "role": "transport-play",
                        "shape": "rounded-rectangle",
                        "style": "gloss2",
                        "titles.default": {
                            "normal": {
                                "font": "FontAwesome@32",
                                "foreground-color": "white",
                                "paragraph-style.alignment": "center",
                                "icon-name": "play"
                            },
                            "highlighted": {
                                "font": "FontAwesome@32",
                                "foreground-color": "#00AFFFFF",
                                "paragraph-style.alignment": "center",
                                "icon-name": "play"
                            },
                            "disabled": {
                                "font": "FontAwesome@32",
                                "foreground-color": "#7F7F7FFF",
                                "paragraph-style.alignment": "center",
                                "icon-name": "play"
                            }
                        },
                        "backgroundColors.default.normal": "#060606FF",
                        "titleEdgeInsets": "{20, 20, 20, 20}"
                    },
                    {
                        "uuid": "7754F230-C17E-4333-AD7F-202A34AB71E1",
                        "name": "Button Pause",
                        "elementType": "button",
                        "role": "transport-pause",
                        "shape": "rounded-rectangle",
                        "style": "gloss2",
                        "titles.default": {
                            "normal": {
                                "font": "FontAwesome@32",
                                "foreground-color": "white",
                                "paragraph-style.alignment": "center",
                                "icon-name": "pause"
                            },
                            "highlighted": {
                                "font": "FontAwesome@32",
                                "foreground-color": "#00AFFFFF",
                                "paragraph-style.alignment": "center",
                                "icon-name": "pause"
                            },
                            "disabled": {
                                "font": "FontAwesome@32",
                                "foreground-color": "#7F7F7FFF",
                                "paragraph-style.alignment": "center",
                                "icon-name": "pause"
                            }
                        },
                        "backgroundColors.default.normal": "#060606FF",
                        "titleEdgeInsets": "{20, 20, 20, 20}"
                    },
                    {
                        "uuid": "D4F04A8A-C2CA-4235-8C6E-080AD7DA5A3B",
                        "name": "Button Rewind",
                        "elementType": "button",
                        "role": "transport-rewind",
                        "shape": "rounded-rectangle",
                        "style": "gloss2",
                        "titles.default": {
                            "normal": {
                                "font": "FontAwesome@32",
                                "foreground-color": "white",
                                "paragraph-style.alignment": "center",
                                "icon-name": "backward"
                            },
                            "highlighted": {
                                "font": "FontAwesome@32",
                                "foreground-color": "#00AFFFFF",
                                "paragraph-style.alignment": "center",
                                "icon-name": "backward"
                            },
                            "disabled": {
                                "font": "FontAwesome@32",
                                "foreground-color": "#7F7F7FFF",
                                "paragraph-style.alignment": "center",
                                "icon-name": "backward"
                            }
                        },
                        "backgroundColors.default.normal": "#060606FF",
                        "titleEdgeInsets": "{20, 20, 20, 20}"
                    },
                    {
                        "uuid": "804894ED-2BA4-467D-A7E2-43E45ECC946B",
                        "name": "Button Fast Forward",
                        "elementType": "button",
                        "role": "transport-fast-forward",
                        "shape": "rounded-rectangle",
                        "style": "gloss2",
                        "titles.default": {
                            "normal": {
                                "font": "FontAwesome@32",
                                "foreground-color": "white",
                                "paragraph-style.alignment": "center",
                                "icon-name": "fast-forward"
                            },
                            "highlighted": {
                                "font": "FontAwesome@32",
                                "foreground-color": "#00AFFFFF",
                                "paragraph-style.alignment": "center",
                                "icon-name": "fast-forward"
                            },
                            "disabled": {
                                "font": "FontAwesome@32",
                                "foreground-color": "#7F7F7FFF",
                                "paragraph-style.alignment": "center",
                                "icon-name": "fast-forward"
                            }
                        },
                        "backgroundColors.default.normal": "#060606FF",
                        "titleEdgeInsets": "{20, 20, 20, 20}"
                    },
                    {
                        "uuid": "5996C324-C978-4AE8-97BA-4F5468CCDEFB",
                        "name": "Button Stop",
                        "elementType": "button",
                        "role": "transport-stop",
                        "shape": "rounded-rectangle",
                        "style": "gloss2",
                        "titles.default": {
                            "normal": {
                                "font": "FontAwesome@32",
                                "foreground-color": "white",
                                "paragraph-style.alignment": "center",
                                "icon-name": "stop"
                            },
                            "highlighted": {
                                "font": "FontAwesome@32",
                                "foreground-color": "#00AFFFFF",
                                "paragraph-style.alignment": "center",
                                "icon-name": "stop"
                            },
                            "disabled": {
                                "font": "FontAwesome@32",
                                "foreground-color": "#7F7F7FFF",
                                "paragraph-style.alignment": "center",
                                "icon-name": "stop"
                            }
                        },
                        "backgroundColors.default.normal": "#060606FF",
                        "titleEdgeInsets": "{20, 20, 20, 20}"
                    },
                    {
                        "uuid": "4BD189E1-996D-4667-B1C0-80C43BC27445",
                        "name": "Button Replay",
                        "elementType": "button",
                        "role": "transport-replay",
                        "shape": "rounded-rectangle",
                        "style": "gloss2",
                        "titles.default": {
                            "normal": {
                                "font": "FontAwesome@32",
                                "foreground-color": "white",
                                "paragraph-style.alignment": "center",
                                "icon-name": "step-backward"
                            },
                            "highlighted": {
                                "font": "FontAwesome@32",
                                "foreground-color": "#00AFFFFF",
                                "paragraph-style.alignment": "center",
                                "icon-name": "step-backward"
                            },
                            "disabled": {
                                "font": "FontAwesome@32",
                                "foreground-color": "#7F7F7FFF",
                                "paragraph-style.alignment": "center",
                                "icon-name": "step-backward"
                            }
                        },
                        "backgroundColors.default.normal": "#060606FF",
                        "titleEdgeInsets": "{20, 20, 20, 20}"
                    },
                    {
                        "uuid": "051E7613-FE45-47CE-AE8A-F50B776348AC",
                        "name": "Tuck",
                        "elementType": "button",
                        "role": "tuck",
                        "shape": "rounded-rectangle",
                        "style": "gloss2",
                        "titles.default.normal": {
                            "font": "HelveticaNeue@20",
                            "foreground-color": "white",
                            "stroke-color": "white@50%",
                            "stroke-width": -2,
                            "text-effect": "letter-press",
                            "text": "▼"
                        },
                        "backgroundColors.default.normal": "#060606FF",
                        "titleEdgeInsets": "{20, 20, 20, 20}"
                    },
                    {
                        "uuid": "08FF87FF-685F-4A56-A40C-BF954852152B",
                        "name": "Button Skip",
                        "elementType": "button",
                        "role": "transport-skip",
                        "shape": "rounded-rectangle",
                        "style": "gloss2",
                        "titles.default": {
                            "normal": {
                                "font": "FontAwesome@32",
                                "foreground-color": "white",
                                "paragraph-style.alignment": "center",
                                "icon-name": "step-forward"
                            },
                            "highlighted": {
                                "font": "FontAwesome@32",
                                "foreground-color": "#00AFFFFF",
                                "paragraph-style.alignment": "center",
                                "icon-name": "step-forward"
                            },
                            "disabled": {
                                "font": "FontAwesome@32",
                                "foreground-color": "#7F7F7FFF",
                                "paragraph-style.alignment": "center",
                                "icon-name": "step-forward"
                            }
                        },
                        "backgroundColors.default.normal": "#060606FF",
                        "titleEdgeInsets": "{20, 20, 20, 20}"
                    },
                    {
                        "uuid": "FC1F0B10-D228-48E5-940E-997D6DD3ED67",
                        "name": "Button Record",
                        "elementType": "button",
                        "role": "transport-record",
                        "shape": "rounded-rectangle",
                        "style": "gloss2",
                        "titles.default": {
                            "normal": {
                                "font": "FontAwesome@32",
                                "foreground-color": "white",
                                "paragraph-style.alignment": "center",
                                "icon-name": "circle"
                            },
                            "highlighted": {
                                "font": "FontAwesome@32",
                                "foreground-color": "#00AFFFFF",
                                "paragraph-style.alignment": "center",
                                "icon-name": "circle"
                            },
                            "disabled": {
                                "font": "FontAwesome@32",
                                "foreground-color": "#7F7F7FFF",
                                "paragraph-style.alignment": "center",
                                "icon-name": "circle"
                            }
                        },
                        "backgroundColors.default.normal": "#060606FF",
                        "titleEdgeInsets": "{20, 20, 20, 20}"
                    }
                ]
            },
            {
                "uuid": "A6394F58-79C6-4B6C-962D-1DDD6BE1C36F",
                "name": "Selection Panel",
                "elementType": "button-group",
                "role": "selection-panel",
                "subtype": "right1",
                "shape": "rounded-rectangle",
                "constraints": {
                    "index": {
                        "buttonSTB": "60FBB7D9-D48A-42E5-A6FD-B47FC13EC23F",
                        "buttonTV": "DDF69EC8-CE1A-45A0-8721-CD91DBEA2135",
                        "selectionPanel": "A6394F58-79C6-4B6C-962D-1DDD6BE1C36F"
                    },
                    "format": [
                        "buttonSTB.bottom = buttonTV.top",
                        "buttonSTB.centerX = selectionPanel.centerX",
                        "buttonSTB.top = selectionPanel.top",
                        "buttonSTB.width = selectionPanel.width",
                        "buttonTV.bottom = selectionPanel.bottom",
                        "buttonTV.centerX = buttonSTB.centerX",
                        "buttonTV.height = buttonSTB.height",
                        "buttonTV.width = buttonSTB.width",
                        "selectionPanel.height ≥ 240",
                        "selectionPanel.width = 150"
                    ]
                },
                "backgroundColor": "white@75%",
                "subelements": [
                    {
                        "uuid": "60FBB7D9-D48A-42E5-A6FD-B47FC13EC23F",
                        "name": "Button STB",
                        "elementType": "button",
                        "key": "default",
                        "role": "selection-panel",
                        "shape": "rounded-rectangle",
                        "style": "gloss2",
                        "titles.default.normal": {
                            "font": "HelveticaNeue@20",
                            "foreground-color": "white",
                            "stroke-color": "white@50%",
                            "stroke-width": -2,
                            "text": "STB"
                        },
                        "backgroundColors.default.normal": "#060606FF",
                        "titleEdgeInsets": "{20, 20, 20, 20}"
                    },
                    {
                        "uuid": "DDF69EC8-CE1A-45A0-8721-CD91DBEA2135",
                        "name": "Button TV",
                        "elementType": "button",
                        "key": "tv",
                        "role": "selection-panel",
                        "shape": "rounded-rectangle",
                        "style": "gloss2",
                        "titles.default.normal": {
                            "font": "HelveticaNeue@20",
                            "foreground-color": "white",
                            "stroke-color": "white@50%",
                            "stroke-width": -2,
                            "text": "TV"
                        },
                        "backgroundColors.default.normal": "#060606FF",
                        "titleEdgeInsets": "{20, 20, 20, 20}"
                    }
                ]
            },
            {
                "uuid": "7521F420-F677-44C9-97BA-4AF836779C21",
                "name": "Left Overlay Panel",
                "elementType": "button-group",
                "role": "panel",
                "subtype": "left1",
                "constraints": {
                    "index": {
                        "menu": "84B5AAD7-F716-49E4-B2DC-F9654CD5EA83",
                        "lastReturn": "1490C210-7F20-4276-810D-232396713B76",
                        "onDemandSource": "93A20B92-6A22-4DEC-802A-D735A1EBA583",
                        "tuckPanel": "E205BA81-90BD-4943-B2F5-6230AD2D95E9",
                        "mute": "66E58C75-BC33-4E25-A4AE-876E37FA991E",
                        "tVAudioInput": "CA88D652-A7F3-4EBE-ABC0-E559CE6AF337",
                        "leftOverlayPanel": "7521F420-F677-44C9-97BA-4AF836779C21",
                        "exit": "5EBDC469-0E9E-4720-A65E-86F6EF652635",
                        "dVRAudioInput": "447B0C03-6390-47B3-8F66-FA58E79AAE81"
                    },
                    "format": [
                        "mute.right = leftOverlayPanel.right - 4",
                        "mute.height = onDemandSource.height",
                        "mute.left = leftOverlayPanel.left + 4",
                        "tVAudioInput.height = onDemandSource.height",
                        "tVAudioInput.top = dVRAudioInput.bottom + 4",
                        "exit.top = lastReturn.bottom + 4",
                        "tuckPanel.height = onDemandSource.height",
                        "dVRAudioInput.left = leftOverlayPanel.left + 4",
                        "tVAudioInput.left = leftOverlayPanel.left + 4",
                        "onDemandSource.top = leftOverlayPanel.top + 4",
                        "exit.height = onDemandSource.height",
                        "onDemandSource.right = leftOverlayPanel.right - 4",
                        "lastReturn.top = menu.bottom + 4",
                        "dVRAudioInput.top = exit.bottom + 4",
                        "menu.top = onDemandSource.bottom + 4",
                        "leftOverlayPanel.width = 150",
                        "dVRAudioInput.height = onDemandSource.height",
                        "tVAudioInput.right = leftOverlayPanel.right - 4",
                        "menu.left = leftOverlayPanel.left + 4",
                        "menu.height = onDemandSource.height",
                        "exit.left = leftOverlayPanel.left + 4",
                        "tuckPanel.right = leftOverlayPanel.right - 4",
                        "tuckPanel.top = mute.bottom + 4",
                        "lastReturn.right = leftOverlayPanel.right - 4",
                        "exit.right = leftOverlayPanel.right - 4",
                        "menu.right = leftOverlayPanel.right - 4",
                        "lastReturn.left = leftOverlayPanel.left + 4",
                        "onDemandSource.left = leftOverlayPanel.left + 4",
                        "lastReturn.height = onDemandSource.height",
                        "mute.top = tVAudioInput.bottom + 4",
                        "dVRAudioInput.right = leftOverlayPanel.right - 4",
                        "tuckPanel.bottom = leftOverlayPanel.bottom - 4",
                        "tuckPanel.left = leftOverlayPanel.left + 4"
                    ]
                },
                "backgroundColor": "white@75%",
                "subelements": [
                    {
                        "uuid": "93A20B92-6A22-4DEC-802A-D735A1EBA583",
                        "name": "On Demand / Source",
                        "elementType": "button",
                        "shape": "rounded-rectangle",
                        "style": "gloss2",
                        "commands": {
                            "default": {
                                "class": "sendir",
                                "code.uuid": "B665AE8E-B376-476E-AED5-471294F06ABB"
                            },
                            "tv": {
                                "class": "sendir",
                                "code.uuid": "F39821FE-3AA2-44B9-84C5-BBC275C4623F"
                            }
                        },
                        "titles": {
                            "default.normal": {
                                "font": "HelveticaNeue@20",
                                "foreground-color": "white",
                                "stroke-color": "white@50%",
                                "stroke-width": -2,
                                "text": "On Demand"
                            },
                            "tv.normal": {
                                "font": "HelveticaNeue@20",
                                "foreground-color": "white",
                                "stroke-color": "white@50%",
                                "stroke-width": -2,
                                "text": "Source"
                            }
                        },
                        "backgroundColors.default.normal": "#060606FF",
                        "titleEdgeInsets": "{20, 20, 20, 20}"
                    },
                    {
                        "uuid": "84B5AAD7-F716-49E4-B2DC-F9654CD5EA83",
                        "name": "Menu",
                        "elementType": "button",
                        "shape": "rounded-rectangle",
                        "style": "gloss2",
                        "commands": {
                            "default": {
                                "class": "sendir",
                                "code.uuid": "C2DDF628-8E2B-40C3-B1E2-6DA3AA65E191"
                            },
                            "tv": {
                                "class": "sendir",
                                "code.uuid": "C2DDF628-8E2B-40C3-B1E2-6DA3AA65E191"
                            }
                        },
                        "titles.default.normal": {
                            "font": "HelveticaNeue@20",
                            "foreground-color": "white",
                            "stroke-color": "white@50%",
                            "stroke-width": -2,
                            "text": "Menu"
                        },
                        "backgroundColors.default.normal": "#060606FF",
                        "titleEdgeInsets": "{20, 20, 20, 20}"
                    },
                    {
                        "uuid": "1490C210-7F20-4276-810D-232396713B76",
                        "name": "Last / Return",
                        "elementType": "button",
                        "shape": "rounded-rectangle",
                        "style": "gloss2",
                        "commands": {
                            "default": {
                                "class": "sendir",
                                "code.uuid": "C7CA9E3E-D0A5-42D2-95C7-5F24CC27A565"
                            },
                            "tv": {
                                "class": "sendir",
                                "code.uuid": "C7CA9E3E-D0A5-42D2-95C7-5F24CC27A565"
                            }
                        },
                        "titles": {
                            "default.normal": {
                                "font": "HelveticaNeue@20",
                                "foreground-color": "white",
                                "stroke-color": "white@50%",
                                "stroke-width": -2,
                                "text": "Last"
                            },
                            "tv.normal": {
                                "font": "HelveticaNeue@20",
                                "foreground-color": "white",
                                "stroke-color": "white@50%",
                                "stroke-width": -2,
                                "text": "Return"
                            }
                        },
                        "backgroundColors.default.normal": "#060606FF",
                        "titleEdgeInsets": "{20, 20, 20, 20}"
                    },
                    {
                        "uuid": "5EBDC469-0E9E-4720-A65E-86F6EF652635",
                        "name": "Exit",
                        "elementType": "button",
                        "shape": "rounded-rectangle",
                        "style": "gloss2",
                        "commands": {
                            "default": {
                                "class": "sendir",
                                "code.uuid": "3140A2C4-3795-497D-8660-3D1B87267648"
                            },
                            "tv": {
                                "class": "sendir",
                                "code.uuid": "3140A2C4-3795-497D-8660-3D1B87267648"
                            }
                        },
                        "titles.default.normal": {
                            "font": "HelveticaNeue@20",
                            "foreground-color": "white",
                            "stroke-color": "white@50%",
                            "stroke-width": -2,
                            "text": "Exit"
                        },
                        "backgroundColors.default.normal": "#060606FF",
                        "titleEdgeInsets": "{20, 20, 20, 20}"
                    },
                    {
                        "uuid": "447B0C03-6390-47B3-8F66-FA58E79AAE81",
                        "name": "DVR Audio Input",
                        "elementType": "button",
                        "shape": "rounded-rectangle",
                        "style": "gloss2",
                        "commands.default": {
                            "class": "sendir",
                            "code.uuid": "DB4BE36E-6E24-4331-A3BA-616F1AEA0883"
                        },
                        "titles.default.normal": {
                            "font": "HelveticaNeue@20",
                            "foreground-color": "white",
                            "stroke-color": "white@50%",
                            "stroke-width": -2,
                            "text": "DVR Audio"
                        },
                        "backgroundColors.default.normal": "#060606FF",
                        "titleEdgeInsets": "{20, 20, 20, 20}"
                    },
                    {
                        "uuid": "CA88D652-A7F3-4EBE-ABC0-E559CE6AF337",
                        "name": "TV Audio Input",
                        "elementType": "button",
                        "shape": "rounded-rectangle",
                        "style": "gloss2",
                        "commands.default": {
                            "class": "sendir",
                            "code.uuid": "076B62D3-50D1-4112-A6FE-F540A366D9E9"
                        },
                        "titles.default.normal": {
                            "font": "HelveticaNeue@20",
                            "foreground-color": "white",
                            "stroke-color": "white@50%",
                            "stroke-width": -2,
                            "text": "TV Audio"
                        },
                        "backgroundColors.default.normal": "#060606FF",
                        "titleEdgeInsets": "{20, 20, 20, 20}"
                    },
                    {
                        "uuid": "66E58C75-BC33-4E25-A4AE-876E37FA991E",
                        "name": "Mute",
                        "elementType": "button",
                        "shape": "rounded-rectangle",
                        "style": "gloss2",
                        "commands.default": {
                            "class": "sendir",
                            "code.uuid": "DE4E3022-06CB-451F-B19C-CB8F26A84619"
                        },
                        "titles.default.normal": {
                            "font": "HelveticaNeue@20",
                            "foreground-color": "white",
                            "stroke-color": "white@50%",
                            "stroke-width": -2,
                            "text": "Mute"
                        },
                        "backgroundColors.default.normal": "#060606FF",
                        "titleEdgeInsets": "{20, 20, 20, 20}"
                    },
                    {
                        "uuid": "E205BA81-90BD-4943-B2F5-6230AD2D95E9",
                        "name": "Tuck Panel",
                        "elementType": "button",
                        "role": "tuck",
                        "shape": "rounded-rectangle",
                        "style": "gloss2",
                        "titles.default.normal": {
                            "font": "HelveticaNeue@20",
                            "foreground-color": "white",
                            "stroke-color": "white@50%",
                            "stroke-width": -2,
                            "text-effect": "letter-press",
                            "text": "◀"
                        },
                        "backgroundColors.default.normal": "#060606FF",
                        "titleEdgeInsets": "{20, 20, 20, 20}"
                    }
                ]
            }
        ],
        "panels": {
            "bottom1": "D505193C-C9D5-4D89-9C9F-D0B24EAE6D69",
            "right1": "A6394F58-79C6-4B6C-962D-1DDD6BE1C36F",
            "left1": "7521F420-F677-44C9-97BA-4AF836779C21",
            "top1": "A2EFC284-8F45-45B1-9A4B-DB448A2AEAE7"
        },
        "modes": [
            "default",
            "tv"
        ]
    }
]
