[{ // BOComponentDevice - AV Receiver
    "uuid": "18A7C007-4DED-48D6-9A72-FA63640C49B5",
    "name": "AV Receiver",
    "port": 2,
    "inputPowersOn": true,
    "offCommand": {
        "type": "send ir",
        "code": "12470A9F-CC42-4C31-B261-213DFDA79BEC"
    },
    "alwaysOn": false,
    "codes": [{
        "uuid": "D75B5099-7C81-44D4-B12D-38C36314FAAB",
        "name": "DVD",
        "frequency": 40192,
        "setsDeviceInput": true,
        "offset": 5,
        "onOffPattern": "96,24,48,24,24,24BBBBBCCCCBBC24,790ABCBBBBBCCCCBBCDABCBBBBBCCCCBBC24,4019",
        "repeatCount": 1
    }, {
        "uuid": "060F0E1E-EB34-447E-803C-536E26718C4F",
        "name": "MD/Tape",
        "frequency": 40192,
        "setsDeviceInput": true,
        "offset": 5,
        "onOffPattern": "96,24,48,24,24,24CBCBBCCCCBBC24,839ABCCBCBBCCCCBBCDABCCBCBBCCCCBBC24,4019",
        "repeatCount": 1
    }, {
        "uuid": "DE4E3022-06CB-451F-B19C-CB8F26A84619",
        "name": "Mute",
        "frequency": 40192,
        "setsDeviceInput": false,
        "offset": 5,
        "onOffPattern": "96,24,24,24B48,24BCBBBBBBCCB24,888ABBCBCBBBBBBCCBDABBCBCBBBBBBCCB24,4019",
        "repeatCount": 1
    }, {
        "uuid": "12470A9F-CC42-4C31-B261-213DFDA79BEC",
        "name": "Power",
        "frequency": 40000,
        "setsDeviceInput": false,
        "offset": 1,
        "onOffPattern": "96,23,48,24,24,24BCBCCCCCCBBC24,800",
        "repeatCount": 3
    }, {
        "uuid": "963E6CDB-9341-4D2C-B2A7-254AB7BCBFA2",
        "name": "SA-CD/CD",
        "frequency": 40192,
        "setsDeviceInput": true,
        "offset": 5,
        "onOffPattern": "96,24,48,24,24,24BCCBCCCCCBBC24,863ABCBCCBCCCCCBBCDABCBCCBCCCCCBBC24,4019",
        "repeatCount": 1
    }, {
        "uuid": "67A87FA5-44D0-4595-8A1A-F311F889332A",
        "name": "Source",
        "frequency": 40192,
        "setsDeviceInput": false,
        "offset": 5,
        "onOffPattern": "96,24,48,24B24,24BBBBBCCBBBB24,717ABBCBBBBBCCBBBBDABBCBBBBBCCBBBB24,4019",
        "repeatCount": 1
    }, {
        "uuid": "DB4BE36E-6E24-4331-A3BA-616F1AEA0883",
        "name": "TV/SAT",
        "frequency": 40192,
        "setsDeviceInput": true,
        "offset": 5,
        "onOffPattern": "96,24,24,24,48,24BCBCCBBBBCCB24,839ABCBCBCCBBBBCCBDABCBCBCCBBBBCCB24,4019",
        "repeatCount": 1
    }, {
        "uuid": "7F5A24D2-7C7F-423D-A410-8D8EA85CBF70",
        "name": "Video 1",
        "frequency": 40192,
        "setsDeviceInput": true,
        "offset": 5,
        "onOffPattern": "96,24,24,24,48,24BBBCBBBBBCCB24,888ABCBBBCBBBBBCCBDABCBBBCBBBBBCCB24,4019",
        "repeatCount": 1
    }, {
        "uuid": "7456619C-3B46-4EA6-8F9D-95172B781148",
        "name": "Video 2",
        "frequency": 40192,
        "setsDeviceInput": true,
        "offset": 5,
        "onOffPattern": "96,24,24,24,48,24CCCBBBBBBCCB24,839ABCCCCBBBBBBCCBDABCCCCBBBBBBCCB24,4019",
        "repeatCount": 1
    }, {
        "uuid": "076B62D3-50D1-4112-A6FE-F540A366D9E9",
        "name": "Video 3",
        "frequency": 40192,
        "setsDeviceInput": true,
        "offset": 5,
        "onOffPattern": "96,24,24,24,48,24BBBBCBBBBCCB24,888ABCBBBBCBBBBCCBDABCBBBBCBBBBCCB24,4019",
        "repeatCount": 1
    }, {
        "uuid": "C27992CE-912E-4D75-8938-AE80A0C2F9F0",
        "name": "Volume Down",
        "frequency": 40192,
        "setsDeviceInput": false,
        "offset": 5,
        "onOffPattern": "96,24,48,24B24,24CBCCCCCCBBC24,863ABBCCBCCCCCCBBCDABBCCBCCCCCCBBC24,4019",
        "repeatCount": 1
    }, {
        "uuid": "DFBB376D-E061-448C-922C-32B20F69D11C",
        "name": "Volume Up",
        "frequency": 40192,
        "setsDeviceInput": false,
        "offset": 5,
        "onOffPattern": "96,24,24,24,48,24BBCBBBBBBCCB24,888ABCBBCBBBBBBCCBDABCBBCBBBBBBCCB24,4019",
        "repeatCount": 1
    }]
}, { // BOComponentDevice - Comcast DVR
    "uuid": "F0419941-0226-4D06-A4F0-4F3B70BE23CF",
    "name": "Comcast DVR",
    "port": 1,
    "inputPowersOn": false,
    "alwaysOn": true,
    "codes": [{
        "uuid": "1EA509D5-02BC-4938-9B51-0419A1AE7E09",
        "name": "A",
        "frequency": 38461,
        "setsDeviceInput": false,
        "offset": 1,
        "onOffPattern": "345,172,19,173BB19,86BCCCCCCCCCCB19,1186,345,86,19,3846",
        "repeatCount": 1
    }, {
        "uuid": "2917AF19-1F24-4C05-B414-121995B09B9C",
        "name": "A/V Input",
        "frequency": 38461,
        "setsDeviceInput": false,
        "offset": 1,
        "onOffPattern": "345,172,19,86B19,173BCBBBBBBBCCBC19,1186,345,86,19,3846",
        "repeatCount": 1
    }, {
        "uuid": "09DBC99B-9BA1-428C-AEB0-4D8D25C25138",
        "name": "Asterisk",
        "frequency": 38461,
        "setsDeviceInput": false,
        "offset": 1,
        "onOffPattern": "345,172,19,86B19,173BBBCBBBBBBBBC19,1360,345,86,19,3846",
        "repeatCount": 1
    }, {
        "uuid": "AF73A62B-3B9F-4C42-869A-C7ECC645FF83",
        "name": "B",
        "frequency": 38461,
        "setsDeviceInput": false,
        "offset": 1,
        "onOffPattern": "345,172,19,173BB19,86CBCCCCCCBBBC19,1013,345,86,19,3846",
        "repeatCount": 1
    }, {
        "uuid": "606AE4D8-09BB-41AC-94FA-5E31E2515F31",
        "name": "C",
        "frequency": 38461,
        "setsDeviceInput": false,
        "offset": 1,
        "onOffPattern": "345,172,19,86BB19,173BCBBBBBBBCCB19,1273,345,86,19,3389,345,86,19,3846",
        "repeatCount": 1
    }, {
        "uuid": "9F316A4A-D1CD-47C7-8A84-4540C7E82786",
        "name": "Change",
        "frequency": 38461,
        "setsDeviceInput": false,
        "offset": 1,
        "onOffPattern": "345,172,19,173B19,86CCBCCCCCCBBCB19,1100,345,86,19,3846",
        "repeatCount": 1
    }, {
        "uuid": "034EC537-9817-45BE-A66E-E58C7EC3AEF9",
        "name": "Channel Down",
        "frequency": 38461,
        "setsDeviceInput": false,
        "offset": 1,
        "onOffPattern": "344,173,19,86B19,173CBBBBBBBBBBCB19,1360,345,86,19,3389,345,86,19,3846",
        "repeatCount": 1
    }, {
        "uuid": "11B0541B-5C94-49A0-853A-D8C94A76998B",
        "name": "Channel Up",
        "frequency": 38343,
        "setsDeviceInput": false,
        "offset": 1,
        "onOffPattern": "344,173,19,172B19,86BCCCCCCCCBCBC19,1183,345,86,19,3379,345,86,19,3834",
        "repeatCount": 1
    }, {
        "uuid": "59E46C6E-E5B1-4562-8498-23A4A7DC40D5",
        "name": "D",
        "frequency": 38461,
        "setsDeviceInput": false,
        "offset": 1,
        "onOffPattern": "345,172,19,173,19,86CBCBCCCCCCBCBC19,1186,345,86,19,3846",
        "repeatCount": 1
    }, {
        "uuid": "A4A417A0-F5AA-45E4-839E-F0727EC81A3F",
        "name": "DVR",
        "frequency": 38343,
        "setsDeviceInput": false,
        "offset": 1,
        "onOffPattern": "344,173,19,172,19,86BBBBCCCCCCCCCC19,1183,345,86,19,3379,345,86,19,3834",
        "repeatCount": 1
    }, {
        "uuid": "EE477ADE-805D-46BF-958E-711561A0E621",
        "name": "Down",
        "frequency": 40000,
        "setsDeviceInput": false,
        "offset": 1,
        "onOffPattern": "96,24,24,24,48,24BCCCCBCBCCCBBCBBC24,481",
        "repeatCount": 1,
        "Device Name": "PS3"
    }, {
        "uuid": "E6195194-F7FE-42C2-962A-13A6AA6858E0",
        "name": "Eight",
        "frequency": 38461,
        "setsDeviceInput": false,
        "offset": 1,
        "onOffPattern": "345,172,19,86BB19,173BBBBBBBBBBBC19,1446,345,86,19,3846",
        "repeatCount": 1
    }, {
        "uuid": "60500AB6-9450-4BEA-86AD-CDB74E90A768",
        "name": "Exit",
        "frequency": 38461,
        "setsDeviceInput": false,
        "offset": 1,
        "onOffPattern": "345,172,19,86,19,173BBCBBBBBBBCBCC19,1186,345,86,19,3389,345,86,19,3846",
        "repeatCount": 1
    }, {
        "uuid": "502E0C1F-9524-4271-893C-089A45FF4BCF",
        "name": "Fast Forward",
        "frequency": 38461,
        "setsDeviceInput": false,
        "offset": 1,
        "onOffPattern": "345,172,19,173,19,86BBBCCCCCCCCBCC19,1186,345,86,19,3389,345,86,19,3846",
        "repeatCount": 1
    }, {
        "uuid": "A0112D20-AACE-4616-BC56-494F102D9E68",
        "name": "Favorites",
        "frequency": 38343,
        "setsDeviceInput": false,
        "offset": 1,
        "onOffPattern": "344,173,19,172,19,86BCBCCCCCCCCBCB19,1183,345,86,19,3834",
        "repeatCount": 1
    }, {
        "uuid": "2AFB9A8E-4377-4063-B832-D13200ACF287",
        "name": "FiOS TV",
        "frequency": 38461,
        "setsDeviceInput": false,
        "offset": 1,
        "onOffPattern": "344,173,19,86,19,173CCCCBBBBBBCCCC19,839,345,86,19,3389,345,86,19,3846",
        "repeatCount": 1
    }, {
        "uuid": "40BCAC68-BC65-4AD4-A5F9-39A541AEF71E",
        "name": "Five",
        "frequency": 38461,
        "setsDeviceInput": false,
        "offset": 1,
        "onOffPattern": "345,172,19,173,19,86BCCCCCCCCCBBCB19,1186,345,86,19,3846",
        "repeatCount": 1
    }, {
        "uuid": "4D24C204-E3FC-4473-A438-38E5B6EE3FE6",
        "name": "Four",
        "frequency": 38461,
        "setsDeviceInput": false,
        "offset": 1,
        "onOffPattern": "345,172,19,86B19,173BBBBBBBBBBBCC19,1360,345,86,19,3846",
        "repeatCount": 1
    }, {
        "uuid": "CC3DAB57-1897-44CB-AA05-6B48CBE96A6D",
        "name": "Guide",
        "frequency": 38461,
        "setsDeviceInput": false,
        "offset": 1,
        "onOffPattern": "345,172,19,86BBB19,173CBBBBBBCBCC19,1186,345,86,19,3389,345,86,19,3846",
        "repeatCount": 1
    }, {
        "uuid": "456D6184-88CF-473C-BF42-16ABF13D1F10",
        "name": "Info",
        "frequency": 38461,
        "setsDeviceInput": false,
        "offset": 1,
        "onOffPattern": "345,172,19,173B19,86CBBCCCCCCCBCB19,1100,345,86,19,3846",
        "repeatCount": 1
    }, {
        "uuid": "22CC7A87-633C-4DF9-A6C8-BDBBF9613D62",
        "name": "Last",
        "frequency": 38000,
        "setsDeviceInput": false,
        "offset": 1,
        "onOffPattern": "345,171,19,172B19,85CBCCCCCCCCCBB19,760",
        "repeatCount": 1
    }, {
        "uuid": "7CB204B0-2837-4612-BF3D-6638D8B3D93B",
        "name": "Left",
        "frequency": 40000,
        "setsDeviceInput": false,
        "offset": 1,
        "onOffPattern": "96,24,48,24B24,24BBBBCBCBBBCCBCCB24,481",
        "repeatCount": 1,
        "Device Name": "PS3"
    }, {
        "uuid": "95F080FE-4622-405F-8429-04038123A57D",
        "name": "Menu",
        "frequency": 38461,
        "setsDeviceInput": false,
        "offset": 1,
        "onOffPattern": "345,172,19,173,19,86CBBCCCCCCCCBBC19,1186,345,86,19,3389,345,86,19,3846",
        "repeatCount": 1
    }, {
        "uuid": "4DDE9552-4EE5-492E-98F4-8EF6600CED85",
        "name": "Next",
        "frequency": 40000,
        "setsDeviceInput": false,
        "offset": 1,
        "onOffPattern": "96,24,48,24,24,24CCBBCCBCBBBCCBCCB24,528",
        "repeatCount": 1,
        "Device Name": "PS3"
    }, {
        "uuid": "019887BD-C57E-4CBD-A8C0-62C1167601D9",
        "name": "Nine",
        "frequency": 38461,
        "setsDeviceInput": false,
        "offset": 1,
        "onOffPattern": "345,172,19,173,19,86,CBCCCCCCCCBBBC19,1186,345,86,19,3846",
        "repeatCount": 1
    }, {
        "uuid": "E551D890-CFC0-4000-BE8C-06873C8AECDB",
        "name": "OK",
        "frequency": 38461,
        "setsDeviceInput": false,
        "offset": 1,
        "onOffPattern": "345,172,19,173,19,86CCBCCCCCCCCBBB19,1186,345,86,19,3389,345,86,19,3846",
        "repeatCount": 1
    }, {
        "uuid": "B665AE8E-B376-476E-AED5-471294F06ABB",
        "name": "On Demand",
        "frequency": 38343,
        "setsDeviceInput": false,
        "offset": 1,
        "onOffPattern": "344,173,19,86,19,172BCCBBBBBBBCBCB19,1183,345,86,19,3834",
        "repeatCount": 1
    }, {
        "uuid": "0313E4A0-996F-4968-8DAB-0C799BD4D2A6",
        "name": "One",
        "frequency": 38461,
        "setsDeviceInput": false,
        "offset": 1,
        "onOffPattern": "345,172,19,173,19,86,CCCCCCCCCCBBBB19,1186,345,86,19,3389,345,86,19,3846",
        "repeatCount": 1
    }, {
        "uuid": "98005E8A-2060-4EFD-9119-51222C5F1E02",
        "name": "Options",
        "frequency": 38461,
        "setsDeviceInput": false,
        "offset": 1,
        "onOffPattern": "344,173,19,86,19,173BBBBCBBBBBBCBC19,1273,345,86,19,3846",
        "repeatCount": 1
    }, {
        "uuid": "15ADF1D8-45C8-4453-B834-EA9896C911D4",
        "name": "PIP",
        "frequency": 38461,
        "setsDeviceInput": false,
        "offset": 1,
        "onOffPattern": "345,172,19,86,19,173BBBCBBBBBBBBCC19,1273,345,86,19,3389E19,3846",
        "repeatCount": 1
    }, {
        "uuid": "8A77DAEA-8B71-4525-917F-916AA636AEBA",
        "name": "Page Down",
        "frequency": 38000,
        "setsDeviceInput": false,
        "offset": 1,
        "onOffPattern": "343,172,19,172B19,86BBBCCCCCCCBCC19,1100,343,86,19,3377",
        "repeatCount": 1
    }, {
        "uuid": "8F9E00ED-FAFA-40B3-A1FA-01B0DF073A75",
        "name": "Page Up",
        "frequency": 38000,
        "setsDeviceInput": false,
        "offset": 1,
        "onOffPattern": "343,172,19,86,19,172BCCCBBBBBBCCBB19,1100,343,86,19,3377",
        "repeatCount": 1
    }, {
        "uuid": "5AA092F8-2D93-437F-B3D0-4006E52DC371",
        "name": "Pause",
        "frequency": 40000,
        "setsDeviceInput": false,
        "offset": 1,
        "onOffPattern": "96,24,48,24,24,24CBBBCCBCBBBCCBCCB24,504",
        "repeatCount": 1,
        "Device Name": "PS3"
    }, {
        "uuid": "7EE63EAB-1054-4DF7-A66B-9E51816AB8D0",
        "name": "Play",
        "frequency": 40000,
        "setsDeviceInput": false,
        "offset": 1,
        "onOffPattern": "96,24,24,24,48,24BBCCBBCBCCCBBCBBC24,529",
        "repeatCount": 1,
        "Device Name": "PS3"
    }, {
        "uuid": "49071768-554E-4D9D-B8E1-26686E07E036",
        "name": "Pound",
        "frequency": 38461,
        "setsDeviceInput": false,
        "offset": 1,
        "onOffPattern": "345,172,19,86BBBBB19,173BBBBBBBCC19,1360,345,86,19,3389E19,3846",
        "repeatCount": 1
    }, {
        "uuid": "FEA29DF1-DA83-4775-9C73-85291A51961C",
        "name": "Prev",
        "frequency": 38343,
        "setsDeviceInput": false,
        "offset": 1,
        "onOffPattern": "344,173,19,86B19,172CCCBBBBBBCBBB19,1183,345,86,19,3379,345,86,19,3834",
        "repeatCount": 1
    }, {
        "uuid": "C613F7A8-5089-4440-B427-C121165DE70C",
        "name": "Record",
        "frequency": 38461,
        "setsDeviceInput": false,
        "offset": 1,
        "onOffPattern": "345,172,19,173,19,86CCBBCCCCCCCCBB19,1186,345,86,19,3389E19,3846",
        "repeatCount": 1
    }, {
        "uuid": "3A8A1370-8842-42C7-9FB3-F01BDCCA9475",
        "name": "Rewind",
        "frequency": 38461,
        "setsDeviceInput": false,
        "offset": 1,
        "onOffPattern": "345,172,19,86,19,173CCCBBBBBBBCBBB19,1186,345,86,19,3846",
        "repeatCount": 1
    }, {
        "uuid": "0BBC99B9-E435-490E-ACE7-DF53DDD4E2F7",
        "name": "Right",
        "frequency": 40000,
        "setsDeviceInput": false,
        "offset": 1,
        "onOffPattern": "96,24,24,24B48,24CCCCBCBCCCBBCBBC24,481",
        "repeatCount": 1,
        "Device Name": "PS3"
    }, {
        "uuid": "B9007475-33AA-4CD7-87E7-3EEF413486FD",
        "name": "Seven",
        "frequency": 38461,
        "setsDeviceInput": false,
        "offset": 1,
        "onOffPattern": "345,172,19,173BB19,86CCCCCCCCBCCB19,1186,345,86,19,3389E19,3846",
        "repeatCount": 1
    }, {
        "uuid": "E57C7D62-3597-45B0-9B80-45F5559F7C18",
        "name": "Six",
        "frequency": 38461,
        "setsDeviceInput": false,
        "offset": 1,
        "onOffPattern": "345,172,19,86,19,173CBBBBBBBBBBCBC19,1273,345,86,19,3389E19,3846",
        "repeatCount": 1
    }, {
        "uuid": "4376CED6-A57A-4930-B3A7-1A234B86291D",
        "name": "Stop",
        "frequency": 40000,
        "setsDeviceInput": false,
        "offset": 1,
        "onOffPattern": "96,24,24,24BB48,24CCBBCBCCCBBCBBC24,529",
        "repeatCount": 1,
        "Device Name": "PS3"
    }, {
        "uuid": "266FC2EF-2EDB-4A41-A42D-2BC1129DFECA",
        "name": "Three",
        "frequency": 38461,
        "setsDeviceInput": false,
        "offset": 1,
        "onOffPattern": "345,172,19,173B19,86CCCCCCCCCBCBB19,1186,345,86,19,3389E19,3846",
        "repeatCount": 1
    }, {
        "uuid": "1B86BE5A-F8D6-4798-895A-B881E6E623D1",
        "name": "Two",
        "frequency": 38461,
        "setsDeviceInput": false,
        "offset": 1,
        "onOffPattern": "345,172,19,86,19,173BBBBBBBBBBBCCC19,1273,345,86,19,3389E19,3846",
        "repeatCount": 1
    }, {
        "uuid": "1C8D165D-4BCD-4CC7-B89F-8FAF9047B0A5",
        "name": "Up",
        "frequency": 40000,
        "setsDeviceInput": false,
        "offset": 1,
        "onOffPattern": "96,24,48,24,24,24CBBBBCBCBBBCCBCCB24,481",
        "repeatCount": 1,
        "Device Name": "PS3"
    }, {
        "uuid": "0900A7E5-23C9-4F6E-9D90-1CEDB9685421",
        "name": "Widgets",
        "frequency": 38343,
        "setsDeviceInput": false,
        "offset": 1,
        "onOffPattern": "344,173,19,172B19,86CCCBCCCCCBCCB19,1183,345,86,19,3834",
        "repeatCount": 1
    }, {
        "uuid": "4D359D0D-BBE0-4BF5-85D3-9BF2CD338563",
        "name": "Zero",
        "frequency": 38461,
        "setsDeviceInput": false,
        "offset": 1,
        "onOffPattern": "345,172,19,86BBBBBBBBBBBBBBB19,1620,345,86,19,3846",
        "repeatCount": 1
    }]
}, { // BOComponentDevice - PS3
    "uuid": "DB69F934-E193-4C45-9598-1D5155B8E6E5",
    "name": "PS3",
    "port": 3,
    "inputPowersOn": false,
    "alwaysOn": false,
    "powerOn": {
        "type": "send ir",
        "code": "29F4A5B7-B9DD-4348-8C0F-EC36BC6CE1B3"
    },
    "powerOff": {
        "type": "send ir",
        "code": "9326516F-1923-4461-AD31-E726B4AAAFB1"
    },
    "codes": [{
        "uuid": "D64D0568-E108-4A53-B8FA-D63FDA4DE76F",
        "name": "0",
        "frequency": 40000,
        "setsDeviceInput": false,
        "offset": 1,
        "onOffPattern": "96,24,48,24,24,24CBCCCCBCBBBCCBCCB24,553",
        "repeatCount": 1
    }, {
        "uuid": "8394CC1B-FAA6-4B2E-8F0D-DDF46B10E781",
        "name": "1",
        "frequency": 40000,
        "setsDeviceInput": false,
        "offset": 1,
        "onOffPattern": "96,24,24,24BBBBBBB48,24BCCCBBCBBC24,601",
        "repeatCount": 1
    }, {
        "uuid": "9A90A48A-3F92-4340-ADC0-1D24830E33D9",
        "name": "2",
        "frequency": 40000,
        "setsDeviceInput": false,
        "offset": 1,
        "onOffPattern": "96,24,48,24,24,24CCCCCCBCBBBCCBCCB24,576",
        "repeatCount": 1
    }, {
        "uuid": "2099F1F4-0DB4-4D8E-B65D-8324769BBBB1",
        "name": "3",
        "frequency": 40000,
        "setsDeviceInput": false,
        "offset": 1,
        "onOffPattern": "96,24,24,24,48,24BBBBBBCBCCCBBCBBC24,577",
        "repeatCount": 1
    }, {
        "uuid": "652CD5EC-E984-44FC-BE68-01A1FFE66B82",
        "name": "4",
        "frequency": 40000,
        "setsDeviceInput": false,
        "offset": 1,
        "onOffPattern": "96,24,48,24B24,24CCCCCBCBBBCCBCCB24,553",
        "repeatCount": 1
    }, {
        "uuid": "DD9BFB37-60C0-4BC9-BEC3-EA98A6F652A8",
        "name": "5",
        "frequency": 40000,
        "setsDeviceInput": false,
        "offset": 1,
        "onOffPattern": "96,24,24,24B48,24BBBBBCBCCCBBCBBC24,576",
        "repeatCount": 1
    }, {
        "uuid": "9557B6B2-35E0-41D5-A57B-A7C235C655AA",
        "name": "6",
        "frequency": 40000,
        "setsDeviceInput": false,
        "offset": 1,
        "onOffPattern": "96,24,48,24,24,24BCCCCCBCBBBCCBCCB24,553",
        "repeatCount": 1
    }, {
        "uuid": "BB4DBBDD-9A10-4D54-9B8B-3934D8A08F10",
        "name": "7",
        "frequency": 40000,
        "setsDeviceInput": false,
        "offset": 1,
        "onOffPattern": "96,24,24,24,48,24CBBBBBCBCCCBBCBBC24,553",
        "repeatCount": 1
    }, {
        "uuid": "A53B4450-64FF-4439-BDEC-72D3C4826BC9",
        "name": "8",
        "frequency": 40000,
        "setsDeviceInput": false,
        "offset": 1,
        "onOffPattern": "96,24,48,24BB24,24CCCCBCBBBCCBCCB24,528",
        "repeatCount": 1
    }, {
        "uuid": "CF0712CF-5DF1-4C86-8B6C-6271E46FB214",
        "name": "9",
        "frequency": 40000,
        "setsDeviceInput": false,
        "offset": 1,
        "onOffPattern": "96,24,24,24BB48,24BBBBCBCCCBBCBBC24,577",
        "repeatCount": 1
    }, {
        "uuid": "A118ADE1-499A-46C3-9526-C52B1A87490E",
        "name": "Angle",
        "frequency": 40000,
        "setsDeviceInput": false,
        "offset": 1,
        "onOffPattern": "96,24,48,24,24,24BCCBBCBCBBBCCBCCB24,504",
        "repeatCount": 1
    }, {
        "uuid": "7B5B2032-AFBC-4C35-8328-F6F10FBA3AD5",
        "name": "Audio",
        "frequency": 40000,
        "setsDeviceInput": false,
        "offset": 1,
        "onOffPattern": "96,24,24,24B48,24BBCCBCBCCCBBCBBC24,528",
        "repeatCount": 1
    }, {
        "uuid": "3DE72227-5AE4-4040-84C9-61EB5EC4318B",
        "name": "BLUE",
        "frequency": 40000,
        "setsDeviceInput": false,
        "offset": 1,
        "onOffPattern": "96,24,24,24B48,24CBCBBCBCCCBBCBBC24,529",
        "repeatCount": 1
    }, {
        "uuid": "4EA5920F-EBCC-4EB9-8B36-89F4B42A04FB",
        "name": "Circle",
        "frequency": 40000,
        "setsDeviceInput": false,
        "offset": 1,
        "onOffPattern": "96,24,48,24,24,24BBBCBCBCBBCBCBBCB48,433",
        "repeatCount": 1
    }, {
        "uuid": "56AA79A9-D682-44B8-9BFA-36283B35F1C7",
        "name": "Clear",
        "frequency": 40000,
        "setsDeviceInput": false,
        "offset": 1,
        "onOffPattern": "96,24,48,24BBB24,24CCCBCBBBCCBCCB24,505",
        "repeatCount": 1
    }, {
        "uuid": "9326516F-1923-4461-AD31-E726B4AAAFB1",
        "name": "Discrete Off",
        "frequency": 39000,
        "setsDeviceInput": false,
        "offset": 1,
        "onOffPattern": "96,24,24,24,48,24CCBCBBCBCCBCBCCBC48,454",
        "repeatCount": 1
    }, {
        "uuid": "29F4A5B7-B9DD-4348-8C0F-EC36BC6CE1B3",
        "name": "Discrete On",
        "frequency": 39000,
        "setsDeviceInput": false,
        "offset": 1,
        "onOffPattern": "96,24,48,24BBB24,24BCCBCBBCBCBBCB48,430",
        "repeatCount": 2
    }, {
        "uuid": "824523FD-5766-4BD2-AE49-11A3DADFAC2B",
        "name": "Display",
        "frequency": 40000,
        "setsDeviceInput": false,
        "offset": 1,
        "onOffPattern": "96,24,24,24B48,24BCBCBCBCCCBBCBBC24,529",
        "repeatCount": 1
    }, {
        "uuid": "48AE2A92-EDB4-4631-A17A-6FF77CCE3877",
        "name": "Eject",
        "frequency": 40000,
        "setsDeviceInput": false,
        "offset": 1,
        "onOffPattern": "96,24,24,24,48,24CBCBBBCBCCBCBCCBC48,485",
        "repeatCount": 1
    }, {
        "uuid": "F10A6315-0F8F-4016-B582-560B5DC14D1B",
        "name": "Enter",
        "frequency": 40000,
        "setsDeviceInput": false,
        "offset": 1,
        "onOffPattern": "96,24,48,24B24,24BCCCCBCBBBCCBCCB24,529",
        "repeatCount": 1
    }, {
        "uuid": "1BDA5CAD-4A91-4911-9DB3-41E36455C279",
        "name": "GREEN",
        "frequency": 40000,
        "setsDeviceInput": false,
        "offset": 1,
        "onOffPattern": "96,24,48,24BBBB24,24CCBCBBBCCBCCB24,481",
        "repeatCount": 1
    }, {
        "uuid": "6CF33950-470E-4B67-A6EB-B11E3DEDB958",
        "name": "L1",
        "frequency": 40000,
        "setsDeviceInput": false,
        "offset": 1,
        "onOffPattern": "96,24,48,24BBBB24,24CCBCBBBCCBCCB24,481",
        "repeatCount": 1
    }, {
        "uuid": "37A0713C-6497-424F-8160-E42DF4996075",
        "name": "L2",
        "frequency": 40000,
        "setsDeviceInput": false,
        "offset": 1,
        "onOffPattern": "96,24,24,24BB48,24CBCBCBCCBCBCCBC48,480",
        "repeatCount": 1
    }, {
        "uuid": "026A52FD-3DA8-449A-9E14-6EEADE841B20",
        "name": "L3",
        "frequency": 40000,
        "setsDeviceInput": false,
        "offset": 1,
        "onOffPattern": "96,24,48,24,24,24CCBCBCBCBBCBCBBCB48,481",
        "repeatCount": 1
    }, {
        "uuid": "4F9D2BFA-467B-4019-BCE3-FBD61974D6B5",
        "name": "PS Key",
        "frequency": 40000,
        "setsDeviceInput": false,
        "offset": 1,
        "onOffPattern": "96,24,48,24,24,24BCBCCCBCBBCBCBBCB48,480",
        "repeatCount": 1
    }, {
        "uuid": "29B03F2D-CC9E-4936-990D-7019C32D439F",
        "name": "Popup Menu",
        "frequency": 40000,
        "setsDeviceInput": false,
        "offset": 1,
        "onOffPattern": "96,24,48,24B24,24BBCCCBCBBBCCBCCB24,504",
        "repeatCount": 1
    }, {
        "uuid": "F31E265F-F3F9-4E95-B981-D692B47E4F6E",
        "name": "Previous",
        "frequency": 40000,
        "setsDeviceInput": false,
        "offset": 1,
        "onOffPattern": "96,24,24,24BBB48,24CBBCBCCCBBCBBC24,553",
        "repeatCount": 1
    }, {
        "uuid": "57BE35BD-A5A1-40A5-A081-FCC0EDC00FF4",
        "name": "R1",
        "frequency": 40000,
        "setsDeviceInput": false,
        "offset": 1,
        "onOffPattern": "96,24,48,24B24,24BBCBCBCBBCBCBBCB48,433",
        "repeatCount": 1
    }, {
        "uuid": "FD2670CD-78D9-4D9A-8FD1-A065218CA788",
        "name": "R2",
        "frequency": 40000,
        "setsDeviceInput": false,
        "offset": 1,
        "onOffPattern": "96,24,48,24,24,24CBBCBCBCBBCBCBBCB48,456",
        "repeatCount": 1
    }, {
        "uuid": "EFD08B81-DFF1-4820-8453-8A702A493B27",
        "name": "R3",
        "frequency": 40000,
        "setsDeviceInput": false,
        "offset": 1,
        "onOffPattern": "96,24,24,24,48,24BBCBCBCBCCBCBCCBC48,481",
        "repeatCount": 1
    }, {
        "uuid": "C3FC227A-1EEA-4857-963D-DE4B4B25A779",
        "name": "RED",
        "frequency": 40000,
        "setsDeviceInput": false,
        "offset": 1,
        "onOffPattern": "96,24,48,24,24,24BCBBCCBCBBBCCBCCB24,505",
        "repeatCount": 1
    }, {
        "uuid": "4216B98E-2BF7-45B0-B58E-F66F3FCB74A0",
        "name": "Return",
        "frequency": 40000,
        "setsDeviceInput": false,
        "offset": 1,
        "onOffPattern": "96,24,24,24,48,24CCBBBBCBCCCBBCBBC24,529",
        "repeatCount": 1
    }, {
        "uuid": "B8532807-2EE4-44E5-8709-4DCA94B7D120",
        "name": "Scan Forward",
        "frequency": 40000,
        "setsDeviceInput": false,
        "offset": 1,
        "onOffPattern": "96,24,24,24B48,24BCCBBCBCCCBBCBBC24,528",
        "repeatCount": 1
    }, {
        "uuid": "A877B7A2-6D82-4FE5-8130-7A960F928558",
        "name": "Scan Reverse",
        "frequency": 40000,
        "setsDeviceInput": false,
        "offset": 1,
        "onOffPattern": "96,24,48,24B24,24CBBCCBCBBBCCBCCB24,505",
        "repeatCount": 1
    }, {
        "uuid": "D4D60F7D-5856-459E-8EA2-5601269CAF1A",
        "name": "Select",
        "frequency": 40000,
        "setsDeviceInput": false,
        "offset": 1,
        "onOffPattern": "96,24,24,24BBB48,24BCBCBCCBCBCCBC48,505",
        "repeatCount": 1
    }, {
        "uuid": "EFFFF999-B6AD-4FAA-903D-6D10E184CAAA",
        "name": "Slow/Step Forward",
        "frequency": 40000,
        "setsDeviceInput": false,
        "offset": 1,
        "onOffPattern": "96,24,48,24,24,24CCCBBCBCBBBCCBCCB24,528",
        "repeatCount": 1
    }, {
        "uuid": "56BE7AA7-0A9B-4C6E-8DBA-E15F7BED88E9",
        "name": "Slow/Step Reverse",
        "frequency": 40000,
        "setsDeviceInput": false,
        "offset": 1,
        "onOffPattern": "96,24,24,24BBBB48,24CBCBCCCBBCBBC24,553",
        "repeatCount": 1
    }, {
        "uuid": "CE0436F8-B3F0-4FE1-AF72-1418A5313081",
        "name": "Square",
        "frequency": 40000,
        "setsDeviceInput": false,
        "offset": 1,
        "onOffPattern": "96,24,48,24BBBB24,24BCBCBBCBCBBCB48,409",
        "repeatCount": 1
    }, {
        "uuid": "9D654AC1-6EC4-42FC-A8C5-865169178536",
        "name": "Start",
        "frequency": 40000,
        "setsDeviceInput": false,
        "offset": 1,
        "onOffPattern": "96,24,48,24B24,24CBCBCBCBBCBCBBCB48,456",
        "repeatCount": 1
    }, {
        "uuid": "047F65BA-213C-4EA4-8C39-77BB1791B774",
        "name": "Subtitle",
        "frequency": 40000,
        "setsDeviceInput": false,
        "offset": 1,
        "onOffPattern": "96,24,48,24B24,24CCBBCBCBBBCCBCCB24,504",
        "repeatCount": 1
    }, {
        "uuid": "98A8676E-B792-4F18-800A-8DAF97340843",
        "name": "Time",
        "frequency": 40000,
        "setsDeviceInput": false,
        "offset": 1,
        "onOffPattern": "96,24,24,24BB48,24BCBBCBCCCBBCBBC24,552",
        "repeatCount": 1
    }, {
        "uuid": "B597048F-F4BA-47C0-B63D-0645180A5DFC",
        "name": "Top Menu",
        "frequency": 40000,
        "setsDeviceInput": false,
        "offset": 1,
        "onOffPattern": "96,24,24,24,48,24BCCBBBCBCCCBBCBBC24,529",
        "repeatCount": 1
    }, {
        "uuid": "5D9319EA-FDDD-48CB-939F-2E940CA1B192",
        "name": "Triangle",
        "frequency": 40000,
        "setsDeviceInput": false,
        "offset": 1,
        "onOffPattern": "96,24,24,24B48,24CCBCBCBCCBCBCCBC48,457",
        "repeatCount": 1
    }, {
        "uuid": "585F142F-AE4A-4265-868E-AFE8D39FAFFA",
        "name": "User Macro 1",
        "frequency": 38000,
        "setsDeviceInput": false,
        "offset": 1,
        "onOffPattern": "91,23,46,22B23,23CCBCCBCBBCBCBBCB46,456",
        "repeatCount": 1
    }, {
        "uuid": "7F08A09B-4D34-449B-A42D-A7374A0AD3DF",
        "name": "User Macro 10",
        "frequency": 38000,
        "setsDeviceInput": false,
        "offset": 1,
        "onOffPattern": "91,23,23,23B46,22CBCBBCBCCBCBCCBC46,456",
        "repeatCount": 1
    }, {
        "uuid": "C2EE0B0C-F2EF-4630-8A11-C6C7884A7B66",
        "name": "User Macro 11",
        "frequency": 38000,
        "setsDeviceInput": false,
        "offset": 1,
        "onOffPattern": "91,23,46,22,23,23BBCBCCBCBBCBCBBCB46,433",
        "repeatCount": 1
    }, {
        "uuid": "E354C71E-B0DA-4FB0-A931-305D8DC6D90E",
        "name": "User Macro 2",
        "frequency": 38000,
        "setsDeviceInput": false,
        "offset": 1,
        "onOffPattern": "91,23,23,23B46,22BBCBBCBCCBCBCCBC46,479",
        "repeatCount": 1
    }, {
        "uuid": "6BCEA77F-E20F-41D0-8A76-073158D4296B",
        "name": "User Macro 3",
        "frequency": 38000,
        "setsDeviceInput": false,
        "offset": 1,
        "onOffPattern": "91,23,46,22,23,23BCCBCCBCBBCBCBBCB46,456",
        "repeatCount": 1
    }, {
        "uuid": "7ECA30E3-A5C4-4AC8-BFFD-7E2BDDA2355C",
        "name": "User Macro 4",
        "frequency": 38000,
        "setsDeviceInput": false,
        "offset": 1,
        "onOffPattern": "91,23,23,23,46,22CBBCBBCBCCBCBCCBC46,456",
        "repeatCount": 1
    }, {
        "uuid": "2C37E976-6F24-44B8-8210-B61F68D37AA1",
        "name": "User Macro 5",
        "frequency": 38000,
        "setsDeviceInput": false,
        "offset": 1,
        "onOffPattern": "91,23,46,22BB23,23CBCCBCBBCBCBBCB46,433",
        "repeatCount": 1
    }, {
        "uuid": "99C71A03-4E3E-41F8-B1C0-EEA0618344FA",
        "name": "User Macro 6",
        "frequency": 38000,
        "setsDeviceInput": false,
        "offset": 1,
        "onOffPattern": "91,23,23,23BB46,22BCBBCBCCBCBCCBC46,479",
        "repeatCount": 1
    }, {
        "uuid": "0EBFC7F5-89C1-4408-A091-CE3A32D3A7A5",
        "name": "User Macro 7",
        "frequency": 38000,
        "setsDeviceInput": false,
        "offset": 1,
        "onOffPattern": "91,23,46,22,23,23CBCBCCBCBBCBCBBCB46,456",
        "repeatCount": 1
    }, {
        "uuid": "9C8973E3-703D-4124-89F3-C5BA1560FC60",
        "name": "User Macro 8",
        "frequency": 38000,
        "setsDeviceInput": false,
        "offset": 1,
        "onOffPattern": "91,23,23,23,46,22BCBCBBCBCCBCBCCBC46,456",
        "repeatCount": 1
    }, {
        "uuid": "DAEDB03B-05F3-4E6B-84EB-3DDF1BE37009",
        "name": "User Macro 9",
        "frequency": 38000,
        "setsDeviceInput": false,
        "offset": 1,
        "onOffPattern": "91,23,46,22B23,23BCBCCBCBBCBCBBCB46,433",
        "repeatCount": 1
    }, {
        "uuid": "C5C8AD25-8139-49FB-8E38-E4B022C386BC",
        "name": "X",
        "frequency": 40000,
        "setsDeviceInput": false,
        "offset": 1,
        "onOffPattern": "96,24,24,24,48,24CCCBCBCBCCBCBCCBC48,432",
        "repeatCount": 1
    }, {
        "uuid": "87AF0071-7779-48ED-B4F5-116BC3269285",
        "name": "YELLOW",
        "frequency": 40000,
        "setsDeviceInput": false,
        "offset": 1,
        "onOffPattern": "96,24,24,24,48,24BCBCBBCBCCCBBCBBC24,529",
        "repeatCount": 1
    }]
}, { // BOComponentDevice - Samsung TV
    "uuid": "CC67B0D5-13E8-4548-BDBF-7B81CAA85A9F",
    "name": "Samsung TV",
    "port": 3,
    "inputPowersOn": false,
    "alwaysOn": false,
    "powerOn": {
        "type": "send ir",
        "code": "4386551B-5B7B-4017-A187-62AAFBB49399"
    },
    "powerOff": {
        "type": "send ir",
        "code": "45693E54-0E98-4D15-89D5-97E89488EDCE"
    },
    "codes": [{
        "uuid": "91426BF0-F443-408A-9983-BD85FA78D19F",
        "name": "3D",
        "frequency": 38109,
        "setsDeviceInput": false,
        "offset": 1,
        "onOffPattern": "171,171,21,64BB21,21CCCCBBBCCCCCBBBBBCCBCCCCCBBC21,1776ABBBCCCCCBBBCCCCCBBBBBCCBCCCCCBBCDABBBCCCCCBBBCCCCCBBBBBCCBCCCCCBBCDABBBCCCCCBBBCCCCCBBBBBCCBCCCCCBBCDABBBCCCCCBBBCCCCCBBBBBCCBCCCCCBBC21,4878",
        "repeatCount": 1
    }, {
        "uuid": "2FB22A87-0A17-4E0A-B2B5-116C8DE2A52E",
        "name": "A-Red",
        "frequency": 38109,
        "setsDeviceInput": false,
        "offset": 1,
        "onOffPattern": "171,171,21,64BB21,21CCCCBBBCCCCCCCBBCBBCBBCCBCCB21,1776ABBBCCCCCBBBCCCCCCCBBCBBCBBCCBCCBDABBBCCCCCBBBCCCCCCCBBCBBCBBCCBCCBDABBBCCCCCBBBCCCCCCCBBCBBCBBCCBCCBDABBBCCCCCBBBCCCCCCCBBCBBCBBCCBCCB21,4878",
        "repeatCount": 1
    }, {
        "uuid": "C8E27CBB-9A11-459A-83E0-F25B3DEDAE46",
        "name": "B-Green",
        "frequency": 38109,
        "setsDeviceInput": false,
        "offset": 1,
        "onOffPattern": "171,171,21,64BB21,21CCCCBBBCCCCCCCBCBCCCBBCBCBBB21,1776ABBBCCCCCBBBCCCCCCCBCBCCCBBCBCBBBDABBBCCCCCBBBCCCCCCCBCBCCCBBCBCBBBDABBBCCCCCBBBCCCCCCCBCBCCCBBCBCBBBDABBBCCCCCBBBCCCCCCCBCBCCCBBCBCBBBDABBBCCCCCBBBCCCCCCCBCBCCCBBCBCBBBDABBBCCCCCBBBCCCCCCCBCBCCCBBCBCBBB21,4878",
        "repeatCount": 1
    }, {
        "uuid": "D69A4DD5-F435-444F-95D5-73FD9D177144",
        "name": "C-Yellow",
        "frequency": 38109,
        "setsDeviceInput": false,
        "offset": 1,
        "onOffPattern": "171,171,21,64BB21,21CCCCBBBCCCCCBCBCBCCCCBCBCBBB21,1776ABBBCCCCCBBBCCCCCBCBCBCCCCBCBCBBBDABBBCCCCCBBBCCCCCBCBCBCCCCBCBCBBBDABBBCCCCCBBBCCCCCBCBCBCCCCBCBCBBBDABBBCCCCCBBBCCCCCBCBCBCCCCBCBCBBBDABBBCCCCCBBBCCCCCBCBCBCCCCBCBCBBBDABBBCCCCCBBBCCCCCBCBCBCCCCBCBCBBB21,4878",
        "repeatCount": 1
    }, {
        "uuid": "81095FCF-5FB3-4637-9D07-55AD8D42AA98",
        "name": "CC",
        "frequency": 38109,
        "setsDeviceInput": false,
        "offset": 1,
        "onOffPattern": "171,171,21,64BB21,21CCCCBBBCCCCCBCBCCBCCCBCBBCBB21,1776ABBBCCCCCBBBCCCCCBCBCCBCCCBCBBCBBDABBBCCCCCBBBCCCCCBCBCCBCCCBCBBCBBDABBBCCCCCBBBCCCCCBCBCCBCCCBCBBCBBDABBBCCCCCBBBCCCCCBCBCCBCCCBCBBCBBDABBBCCCCCBBBCCCCCBCBCCBCCCBCBBCBB21,4878",
        "repeatCount": 1
    }, {
        "uuid": "05E5F1BD-6C44-4B1E-AA16-665CA11AE5A1",
        "name": "Channel Down",
        "frequency": 38109,
        "setsDeviceInput": false,
        "offset": 1,
        "onOffPattern": "171,171,21,64BB21,21CCCCBBBCCCCCCCCCBCCCBBBBCBBB21,1776ABBBCCCCCBBBCCCCCCCCCBCCCBBBBCBBBDABBBCCCCCBBBCCCCCCCCCBCCCBBBBCBBBDABBBCCCCCBBBCCCCCCCCCBCCCBBBBCBBBDABBBCCCCCBBBCCCCCCCCCBCCCBBBBCBBB21,4878",
        "repeatCount": 1
    }, {
        "uuid": "2397C898-879B-4CE2-9FCD-5F5AAD75FC7B",
        "name": "Channel List",
        "frequency": 38109,
        "setsDeviceInput": false,
        "offset": 1,
        "onOffPattern": "171,171,21,64BB21,21CCCCBBBCCCCCBBCBCBBCCCBCBCCB21,1776ABBBCCCCCBBBCCCCCBBCBCBBCCCBCBCCBDABBBCCCCCBBBCCCCCBBCBCBBCCCBCBCCBDABBBCCCCCBBBCCCCCBBCBCBBCCCBCBCCBDABBBCCCCCBBBCCCCCBBCBCBBCCCBCBCCB21,4878",
        "repeatCount": 1
    }, {
        "uuid": "22C6EC83-D81A-40B4-8CCC-A992CCF1F323",
        "name": "Channel Up",
        "frequency": 38109,
        "setsDeviceInput": false,
        "offset": 1,
        "onOffPattern": "171,171,21,64BB21,21,21,22CCCBBBCCCCCCBCCBCCCBCBBCBBB21,1776ABBBCCCCCBBBCCCCCCBCCBCCCBCBBCBBBEABBBCCCCCBBBCCCCCCBCCBCCCBCBBCBBBEABBBCCCCCBBBCCCCCCBCCBCCCBCBBCBBB21,4878",
        "repeatCount": 1
    }, {
        "uuid": "105610F0-F578-4240-9D72-E91E755CD553",
        "name": "Content",
        "frequency": 38109,
        "setsDeviceInput": false,
        "offset": 1,
        "onOffPattern": "171,171,21,64BB21,21CCCCBBBCCCCCBCCBBBBCCBBCCCCB21,1776ABBBCCCCCBBBCCCCCBCCBBBBCCBBCCCCBDABBBCCCCCBBBCCCCCBCCBBBBCCBBCCCCBDABBBCCCCCBBBCCCCCBCCBBBBCCBBCCCCBDABBBCCCCCBBBCCCCCBCCBBBBCCBBCCCCB21,4878",
        "repeatCount": 1
    }, {
        "uuid": "CE1D66BC-10C4-4057-855A-7237B1542B1A",
        "name": "D-Blue",
        "frequency": 38109,
        "setsDeviceInput": false,
        "offset": 1,
        "onOffPattern": "171,171,21,64BB21,21CCCCBBBCCCCCCBBCBCCCBCCBCBBB21,1776ABBBCCCCCBBBCCCCCCBBCBCCCBCCBCBBBDABBBCCCCCBBBCCCCCCBBCBCCCBCCBCBBBDABBBCCCCCBBBCCCCCCBBCBCCCBCCBCBBBDABBBCCCCCBBBCCCCCCBBCBCCCBCCBCBBBDABBBCCCCCBBBCCCCCCBBCBCCCBCCBCBBB21,4878",
        "repeatCount": 1
    }, {
        "uuid": "E8CE4D31-C85D-43C9-802E-D1526C86A151",
        "name": "Dash",
        "frequency": 38109,
        "setsDeviceInput": false,
        "offset": 1,
        "onOffPattern": "171,171,21,64BB21,21CCCCBBBCCCCCBBCCCBCCCCBBBCBB21,1776ABBBCCCCCBBBCCCCCBBCCCBCCCCBBBCBBDABBBCCCCCBBBCCCCCBBCCCBCCCCBBBCBBDABBBCCCCCBBBCCCCCBBCCCBCCCCBBBCBBDABBBCCCCCBBBCCCCCBBCCCBCCCCBBBCBB21,4878",
        "repeatCount": 1
    }, {
        "uuid": "8F6D2E32-CE4E-49C8-9EA1-358755A5946F",
        "name": "Down",
        "frequency": 38109,
        "setsDeviceInput": false,
        "offset": 1,
        "onOffPattern": "171,171,21,64BB21,21CCCCBBBCCCCCBCCCCBBCCBBBBCCB21,1776ABBBCCCCCBBBCCCCCBCCCCBBCCBBBBCCBDABBBCCCCCBBBCCCCCBCCCCBBCCBBBBCCB21,4878",
        "repeatCount": 1
    }, {
        "uuid": "B5B6C73F-483D-48AE-AF56-2D919B231716",
        "name": "Eight",
        "frequency": 38109,
        "setsDeviceInput": false,
        "offset": 1,
        "onOffPattern": "171,171,21,64BB21,21CCCCBBBCCCCCBCBBCCCCCBCCBBBB21,1776ABBBCCCCCBBBCCCCCBCBBCCCCCBCCBBBBDABBBCCCCCBBBCCCCCBCBBCCCCCBCCBBBBDABBBCCCCCBBBCCCCCBCBBCCCCCBCCBBBBDABBBCCCCCBBBCCCCCBCBBCCCCCBCCBBBBDABBBCCCCCBBBCCCCCBCBBCCCCCBCCBBBB21,4878",
        "repeatCount": 1
    }, {
        "uuid": "28B2DBAB-D4B4-45AD-8F4D-FE4492AE7D95",
        "name": "Enter",
        "frequency": 38109,
        "setsDeviceInput": false,
        "offset": 1,
        "onOffPattern": "171,171,21,64BB21,21CCCCBBBCCCCCCCCBCBBCBBBCBCCB21,1776ABBBCCCCCBBBCCCCCCCCBCBBCBBBCBCCBDABBBCCCCCBBBCCCCCCCCBCBBCBBBCBCCBDABBBCCCCCBBBCCCCCCCCBCBBCBBBCBCCBDABBBCCCCCBBBCCCCCCCCBCBBCBBBCBCCBDABBBCCCCCBBBCCCCCCCCBCBBCBBBCBCCBDABBBCCCCCBBBCCCCCCCCBCBBCBBBCBCCB21,4878",
        "repeatCount": 1
    }, {
        "uuid": "3140A2C4-3795-497D-8660-3D1B87267648",
        "name": "Exit",
        "frequency": 38109,
        "setsDeviceInput": false,
        "offset": 1,
        "onOffPattern": "171,171,21,64BB21,21CCCCBBBCCCCCBCBBCBCCCBCCBCBB21,1776ABBBCCCCCBBBCCCCCBCBBCBCCCBCCBCBBDABBBCCCCCBBBCCCCCBCBBCBCCCBCCBCBBDABBBCCCCCBBBCCCCCBCBBCBCCCBCCBCBBDABBBCCCCCBBBCCCCCBCBBCBCCCBCCBCBBDABBBCCCCCBBBCCCCCBCBBCBCCCBCCBCBB21,4878",
        "repeatCount": 1
    }, {
        "uuid": "3BAB007F-BB53-4419-94E0-6905DC8421CD",
        "name": "Fast Forward",
        "frequency": 38109,
        "setsDeviceInput": false,
        "offset": 1,
        "onOffPattern": "171,171,21,64BB21,21CCCCBBBCCCCCCCCBCCBCBBBCBBCB21,1776ABBBCCCCCBBBCCCCCCCCBCCBCBBBCBBCBDABBBCCCCCBBBCCCCCCCCBCCBCBBBCBBCBDABBBCCCCCBBBCCCCCCCCBCCBCBBBCBBCBDABBBCCCCCBBBCCCCCCCCBCCBCBBBCBBCB21,4878",
        "repeatCount": 1
    }, {
        "uuid": "8F0DED3A-F740-43F1-BAB2-408B282D5688",
        "name": "Fav.CH",
        "frequency": 38109,
        "setsDeviceInput": false,
        "offset": 1,
        "onOffPattern": "171,171,21,64BB21,21CCCCBBBCCCCCCCBCCCBCBBCBBBCB21,1776ABBBCCCCCBBBCCCCCCCBCCCBCBBCBBBCBDABBBCCCCCBBBCCCCCCCBCCCBCBBCBBBCBDABBBCCCCCBBBCCCCCCCBCCCBCBBCBBBCB21,4878",
        "repeatCount": 1
    }, {
        "uuid": "F74D33DB-21CA-4A39-90E1-376F0BD8E9C2",
        "name": "Five",
        "frequency": 38109,
        "setsDeviceInput": false,
        "offset": 1,
        "onOffPattern": "171,171,21,64BB21,21CCCCBBBCCCCCBCCBCCCCCBBCBBBB21,1776ABBBCCCCCBBBCCCCCBCCBCCCCCBBCBBBBDABBBCCCCCBBBCCCCCBCCBCCCCCBBCBBBBDABBBCCCCCBBBCCCCCBCCBCCCCCBBCBBBBDABBBCCCCCBBBCCCCCBCCBCCCCCBBCBBBB21,4878",
        "repeatCount": 1
    }, {
        "uuid": "2FCB0343-7EE3-40B6-9D98-B52386CC22EA",
        "name": "Four",
        "frequency": 38109,
        "setsDeviceInput": false,
        "offset": 1,
        "onOffPattern": "171,171,21,64BB21,21CCCCBBBCCCCCCCCBCCCCBBBCBBBB21,1776ABBBCCCCCBBBCCCCCCCCBCCCCBBBCBBBB21,1777ABBBCCCCCBBBCCCCCCCCBCCCCBBBCBBBBDABBBCCCCCBBBCCCCCCCCBCCCCBBBCBBBBDABBBCCCCCBBBCCCCCCCCBCCCCBBBCBBBB21,4878",
        "repeatCount": 1
    }, {
        "uuid": "24882898-51BD-460A-BBB3-A47ADCFF841F",
        "name": "HDMI 1",
        "frequency": 38000,
        "setsDeviceInput": true,
        "offset": 1,
        "onOffPattern": "172,172,21,64BB21,21CCCCBBBCCCCCBCCBCBBBCBBCBCCC21,1673",
        "repeatCount": 1
    }, {
        "uuid": "9B610062-5553-41BB-AB0D-49D787E06A5F",
        "name": "HDMI 2",
        "frequency": 38000,
        "setsDeviceInput": true,
        "offset": 1,
        "onOffPattern": "172,172,21,64BB21,21CCCCBBBCCCCCCBBBBBCBBCCCCCBC21,1673",
        "repeatCount": 1
    }, {
        "uuid": "091DB56C-F35E-4D8C-A49B-3DC47A76542B",
        "name": "HDMI 3",
        "frequency": 38000,
        "setsDeviceInput": true,
        "offset": 1,
        "onOffPattern": "172,172,21,64BB21,21CCCCBBBCCCCCCBCCCCBBBCBBBBCC21,1673",
        "repeatCount": 1
    }, {
        "uuid": "FBB3BC24-1AFA-4AAF-B477-FC28855EE0E5",
        "name": "HDMI 4",
        "frequency": 38000,
        "setsDeviceInput": true,
        "offset": 1,
        "onOffPattern": "172,171,21,65BB21,22CCCCBBBCCCCCBCBCCCBBCBCBBBCC21,1673",
        "repeatCount": 1
    }, {
        "uuid": "4EBF1E15-0353-48B5-B209-51194C73A2AF",
        "name": "HDMI-CEC",
        "frequency": 38109,
        "setsDeviceInput": false,
        "offset": 1,
        "onOffPattern": "171,171,21,64BB21,21CCCCBBBCCCCCCBBCCCBCBCCBBBCB21,1776ABBBCCCCCBBBCCCCCCBBCCCBCBCCBBBCBDABBBCCCCCBBBCCCCCCBBCCCBCBCCBBBCBDABBBCCCCCBBBCCCCCCBBCCCBCBCCBBBCB21,4878",
        "repeatCount": 1
    }, {
        "uuid": "30B1392A-7827-48AB-81DE-CA17439BC738",
        "name": "Info",
        "frequency": 38109,
        "setsDeviceInput": false,
        "offset": 1,
        "onOffPattern": "171,171,21,64BB21,21CCCCBBBCCCCCBBBBBCCCCCCCCBBB21,1776ABBBCCCCCBBBCCCCCBBBBBCCCCCCCCBBBDABBBCCCCCBBBCCCCCBBBBBCCCCCCCCBBBDABBBCCCCCBBBCCCCCBBBBBCCCCCCCCBBBDABBBCCCCCBBBCCCCCBBBBBCCCCCCCCBBBDABBBCCCCCBBBCCCCCBBBBBCCCCCCCCBBBDABBBCCCCCBBBCCCCCBBBBBCCCCCCCCBBB21,4878",
        "repeatCount": 1
    }, {
        "uuid": "31E6CBAC-BA05-42DD-827D-45496EBDC78B",
        "name": "Internet@TV",
        "frequency": 38109,
        "setsDeviceInput": false,
        "offset": 1,
        "onOffPattern": "171,171,21,64BB21,21CCCCBBBCCCCCBBCCBCCBCCBBCBBC21,1776ABBBCCCCCBBBCCCCCBBCCBCCBCCBBCBBCDABBBCCCCCBBBCCCCCBBCCBCCBCCBBCBBCDABBBCCCCCBBBCCCCCBBCCBCCBCCBBCBBCDABBBCCCCCBBBCCCCCBBCCBCCBCCBBCBBCDABBBCCCCCBBBCCCCCBBCCBCCBCCBBCBBC21,4878",
        "repeatCount": 1
    }, {
        "uuid": "FD78049B-A05F-4878-BFBB-A13514120AAD",
        "name": "Left",
        "frequency": 38109,
        "setsDeviceInput": false,
        "offset": 1,
        "onOffPattern": "171,171,21,64BB21,21CCCCBBBCCCCCBCBCCBBCCBCBBCCB21,1776ABBBCCCCCBBBCCCCCBCBCCBBCCBCBBCCBDABBBCCCCCBBBCCCCCBCBCCBBCCBCBBCCB21,4878",
        "repeatCount": 1
    }, {
        "uuid": "955E5FC8-CC37-4347-8395-A7994FFDF17E",
        "name": "Media.P",
        "frequency": 38109,
        "setsDeviceInput": false,
        "offset": 1,
        "onOffPattern": "171,171,21,64BB21,21CCCCBBBCCCCCCCBBCCCBBBCCBBBC21,1776ABBBCCCCCBBBCCCCCCCBBCCCBBBCCBBBCDABBBCCCCCBBBCCCCCCCBBCCCBBBCCBBBCDABBBCCCCCBBBCCCCCCCBBCCCBBBCCBBBCDABBBCCCCCBBBCCCCCCCBBCCCBBBCCBBBCDABBBCCCCCBBBCCCCCCCBBCCCBBBCCBBBCDABBBCCCCCBBBCCCCCCCBBCCCBBBCCBBBC21,4878",
        "repeatCount": 1
    }, {
        "uuid": "C2DDF628-8E2B-40C3-B1E2-6DA3AA65E191",
        "name": "Menu",
        "frequency": 38109,
        "setsDeviceInput": false,
        "offset": 1,
        "onOffPattern": "171,171,21,64BB21,21CCCCBBBCCCCCCBCBBCCCBCBCCBBB21,1776ABBBCCCCCBBBCCCCCCBCBBCCCBCBCCBBBDABBBCCCCCBBBCCCCCCBCBBCCCBCBCCBBBDABBBCCCCCBBBCCCCCCBCBBCCCBCBCCBBBDABBBCCCCCBBBCCCCCCBCBBCCCBCBCCBBB21,4878",
        "repeatCount": 1
    }, {
        "uuid": "81C5B47D-FDE7-44F5-B0AE-B906E81D7503",
        "name": "Mute",
        "frequency": 38109,
        "setsDeviceInput": false,
        "offset": 1,
        "onOffPattern": "171,171,21,64BB21,21CCCCBBBCCCCCBBBBCCCCCCCCBBBB21,1776ABBBCCCCCBBBCCCCCBBBBCCCCCC21,22CBBBBDABBBCCCCCBBBCCCCCBBBBCCCCCCCCBBBBDABBBCCCCCBBBCCCCCBBBBCCCCCCCCBBBBDABBBCCCCCBBBCCCCCBBBBCCCCCCCCBBBBDABBBCCCCCBBBCCCCCBBBBCCCCCCCCBBBB21,4878",
        "repeatCount": 1
    }, {
        "uuid": "EF8A4A0E-BC38-499C-984E-A1FD3A518333",
        "name": "Nine",
        "frequency": 38109,
        "setsDeviceInput": false,
        "offset": 1,
        "onOffPattern": "171,171,21,64BB21,21CCCCBBBCCCCCCBBBCCCCBCCCBBBB21,1776ABBBCCCCCBBBCCCCCCBBBCCCCBCCCBBBBDABBBCCCCCBBBCCCCCCBBBCCCCBCCCBBBBDABBBCCCCCBBBCCCCCCBBBCCCCBCCCBBBBDABBBCCCCCBBBCCCCCCBBBCCCCBCCCBBBBDABBBCCCCCBBBCCCCCCBBBCCCCBCCCBBBB21,4878",
        "repeatCount": 1
    }, {
        "uuid": "E7921E8C-29AB-4ACC-914D-CC4104B5849A",
        "name": "One",
        "frequency": 38109,
        "setsDeviceInput": false,
        "offset": 1,
        "onOffPattern": "171,171,21,64BB21,21CC21,22CBBBCCCCCDDBCCCCCBBCBBBBB21,1776ABBBCCCCCBBBCCCCCCCBCCCCCBBCBBBBBEABBBCCCCCBBBCCCCCCCBCCCCCBBCBBBBBEABBBCCCCCBBBCCCCCCCBCCCCCBBCBBBBB21,4878",
        "repeatCount": 1
    }, {
        "uuid": "B526CC6D-41C4-40A4-9C1D-6F770B106EA1",
        "name": "P.Size",
        "frequency": 38109,
        "setsDeviceInput": false,
        "offset": 1,
        "onOffPattern": "171,171,21,64BB21,21CCCCBBBCCCCCCBBBBBCCBCCCCCBB21,1776ABBBCCCCCBBBCCCCCCBBBBBCCBCCCCCBBDABBBCCCCCBBBCCCCCCBBBBBCCBCCCCCBBDABBBCCCCCBBBCCCCCCBBBBBCCBCCCCCBBDABBBCCCCCBBBCCCCCCBBBBBCCBCCCCCBB21,4878",
        "repeatCount": 1
    }, {
        "uuid": "205237EF-C498-48BA-87C0-05C1E4B39B4D",
        "name": "Pause",
        "frequency": 38109,
        "setsDeviceInput": false,
        "offset": 1,
        "onOffPattern": "171,171,21,64BB21,21CCCCBBBCCCCCCBCBCCBCBCBCBBCB21,1776ABBBCCCCCBBBCCCCCCBCBCCBCBCBCBBCBDABBBCCCCCBBBCCCCCCBCBCCBCBCBCBBCBDABBBCCCCCBBBCCCCCCBCBCCBCBCBCBBCBDABBBCCCCCBBBCCCCCCBCBCCBCBCBCBBCB21,4878",
        "repeatCount": 1
    }, {
        "uuid": "993BE461-7141-4906-A633-BDAE5912CCB6",
        "name": "Play",
        "frequency": 38109,
        "setsDeviceInput": false,
        "offset": 1,
        "onOffPattern": "171,171,21,64BB21,21CCCCBBBCCCCCBBBCCCBCCCCBBBCB21,1776ABBBCCCCCBBBCCCCCBBBCCCBCCCCBBBCBDABBBCCCCCBBBCCCCCBBBCCCBCCCCBBBCBDABBBCCCCCBBBCCCCCBBBCCCBCCCCBBBCB21,4878",
        "repeatCount": 1
    }, {
        "uuid": "8DE8F9DB-2617-4AC9-A9A1-E6D86645DAF7",
        "name": "Power",
        "frequency": 38109,
        "setsDeviceInput": false,
        "offset": 1,
        "onOffPattern": "171,171,21,64BB21,21CCCCBBBCCCCCCBCCCCCCBCBBBBBB21,1776ABBBCCCCCBBBCCCCCCBCCCCCCBCBBBBBBDABBBCCCCCBBBCCCCCCBCCCCCCBCBBBBBBDABBBCCCCCBBBCCCCCCBCCCCCCBCBBBBBBDABBBCCCCCBBBCCCCCCBCCCCCCBCBBBBBBDABBBCCCCCBBBCCCCCCBCCCCCCBCBBBBBB21,4878",
        "repeatCount": 1
    }, {
        "uuid": "45693E54-0E98-4D15-89D5-97E89488EDCE",
        "name": "Power Off",
        "frequency": 38000,
        "setsDeviceInput": false,
        "offset": 1,
        "onOffPattern": "172,172,21,64BB21,21CCCCBBBCCCCCCCCBBCCBBBBCCBBC21,1673",
        "repeatCount": 1
    }, {
        "uuid": "4386551B-5B7B-4017-A187-62AAFBB49399",
        "name": "Power On",
        "frequency": 38000,
        "setsDeviceInput": false,
        "offset": 1,
        "onOffPattern": "172,172,21,64BB21,21CCCCBBBCCCCCBCCBBCCBCBBCCBBC21,1673",
        "repeatCount": 2
    }, {
        "uuid": "F8F018D7-C724-400E-8ED5-B58AF575ECC1",
        "name": "Pre-CH",
        "frequency": 38109,
        "setsDeviceInput": false,
        "offset": 1,
        "onOffPattern": "171,171,21,64BB21,21CCCCBBBCCCCCBBCCBCCCCCBBCBBB21,1776ABBBCCCCCBBBCCCCCBBCCBCCCCCBBCBBBDABBBCCCCCBBBCCCCCBBCCBCCCCCBBCBBBDABBBCCCCCBBBCCCCCBBCCBCCCCCBBCBBBDABBBCCCCCBBBCCCCCBBCCBCCCCCBBCBBB21,4878",
        "repeatCount": 1
    }, {
        "uuid": "8DFC1FC3-9C29-4661-B10C-B3398E3314E3",
        "name": "Record",
        "frequency": 38109,
        "setsDeviceInput": false,
        "offset": 1,
        "onOffPattern": "171,171,21,64BB21,21CCCCBBBCCCCCBCCBCCBCCBBCBBCB21,1776ABBBCCCCCBBBCCCCCBCCBCCBCCBBCBBCBDABBBCCCCCBBBCCCCCBCCBCCBCCBBCBBCBDABBBCCCCCBBBCCCCCBCCBCCBCCBBCBBCBDABBBCCCCCBBBCCCCCBCCBCCBCCBBCBBCB21,4878",
        "repeatCount": 1
    }, {
        "uuid": "C7CA9E3E-D0A5-42D2-95C7-5F24CC27A565",
        "name": "Return",
        "frequency": 38109,
        "setsDeviceInput": false,
        "offset": 1,
        "onOffPattern": "171,171,21,64BB21,21CCCCBBBCCCCCCCCBBCBCBBBCCBCB21,1776ABBBCCCCCBBBCCCCCCCCBBCBCBBBCCBCBDABBBCCCCCBBBCCCCCCCCBBCBCBBBCCBCBDABBBCCCCCBBBCCCCCCCCBBCBCBBBCCBCBDABBBCCCCCBBBCCCCCCCCBBCBCBBBCCBCBDABBBCCCCCBBBCCCCCCCCBBCBCBBBCCBCB21,4878",
        "repeatCount": 1
    }, {
        "uuid": "9612F9A4-2D50-4751-97E2-C9696F268299",
        "name": "Rewind",
        "frequency": 38109,
        "setsDeviceInput": false,
        "offset": 1,
        "onOffPattern": "171,171,21,64BB21,21CCCCBBBCCCCCBCBCCCBCCBCBBBCB21,1776ABBBCCCCCBBBCCCCCBCBCCCBCCBCBBBCBDABBBCCCCCBBBCCCCCBCBCCCBCCBCBBBCBDABBBCCCCCBBBCCCCCBCBCCCBCCBCBBBCBDABBBCCCCCBBBCCCCCBCBCCCBCCBCBBBCB21,4878",
        "repeatCount": 1
    }, {
        "uuid": "19304E22-BA5E-4317-B2AD-1E62F9720233",
        "name": "Right",
        "frequency": 38000,
        "setsDeviceInput": false,
        "offset": 1,
        "onOffPattern": "171,170,21,63BB21,21CCCCBBBCCCCCCBCCCBBCBCBBBCCB21,760",
        "repeatCount": 1
    }, {
        "uuid": "3B7C1FB7-A6FF-4463-8EBC-D1556DB9446C",
        "name": "Seven",
        "frequency": 38109,
        "setsDeviceInput": false,
        "offset": 1,
        "onOffPattern": "171,171,21,64BB21,21CCCCBBBCCCCCCCBBCCCCBBCCBBBB21,1776ABBBCCCCCBBBCCCCCCCBBCCCCBBCCBBBBDABBBCCCCCBBBCCCCCCCBBCCCCBBCCBBBBDABBBCCCCCBBBCCCCCCCBBCCCCBBCCBBBBDABBBCCCCCBBBCCCCCCCBBCCCCBBCCBBBB21,4878",
        "repeatCount": 1
    }, {
        "uuid": "6C8549BB-AA63-4D82-868B-4C381FD12ECF",
        "name": "Six",
        "frequency": 38109,
        "setsDeviceInput": false,
        "offset": 1,
        "onOffPattern": "171,171,21,64BB21,21CCCCBBBCCCCCCBCBCCCCBCBCBBBB21,1776ABBBCCCCCBBBCCCCCCBCBCCCCBCBCBBBBDABBBCCCCCBBBCCCCCCBCBCCCCBCBCBBBBDABBBCCCCCBBBCCCCCCBCBCCCCBCBCBBBBDABBBCCCCCBBBCCCCCCBCBCCCCBCBCBBBBDABBBCCCCCBBBCCCCCCBCBCCCCBCBCBBBB21,4878",
        "repeatCount": 1
    }, {
        "uuid": "F39821FE-3AA2-44B9-84C5-BBC275C4623F",
        "name": "Source",
        "frequency": 38109,
        "setsDeviceInput": false,
        "offset": 1,
        "onOffPattern": "171,171,21,64BB21,21CCCCBBBCCCCCBCCCCCCCCBBBBBBB21,1776ABBBCCCCCBBBCCCCCBCCCCCCCCBBBBBBBDABBBCCCCCBBBCCCCCBCCCCCCCCBBBBBBBDABBBCCCCCBBBCCCCCBCCCCCCCCBBBBBBBDABBBCCCCCBBBCCCCCBCCCCCCCCBBBBBBB21,4878",
        "repeatCount": 1
    }, {
        "uuid": "6D782F7C-9BB7-40B8-8741-CE191636249A",
        "name": "Three",
        "frequency": 38109,
        "setsDeviceInput": false,
        "offset": 1,
        "onOffPattern": "171,171,21,64BB21,21CCCCBBBCCCCCCBBCCCCCBCCBBBBB21,1776ABBBCCCCCBBBCCCCCCBBCCCCCBCCBBBBBDABBBCCCCCBBBCCCCCCBBCCCCCBCCBBBBBDABBBCCCCCBBBCCCCCCBBCCCCCBCCBBBBBDABBBCCCCCBBBCCCCCCBBCCCCCBCCBBBBBDABBBCCCCCBBBCCCCCCBBCCCCCBCCBBBBB21,4878",
        "repeatCount": 1
    }, {
        "uuid": "A32C02D7-6CE0-46C0-8469-8F074C6D96E5",
        "name": "Tools",
        "frequency": 38109,
        "setsDeviceInput": false,
        "offset": 1,
        "onOffPattern": "171,171,21,64BB21,21CCCCBBBCCCCCBBCBCCBCCCBCBBCB21,1776ABBBCCCCCBBBCCCCCBBCBCCBCCCBCBBCBDABBBCCCCCBBBCCCCCBBCBCCBCCCBCBBCBDABBBCCCCCBBBCCCCCBBCBCCBCCCBCBBCBDABBBCCCCCBBBCCCCCBBCBCCBCCCBCBBCBDABBBCCCCCBBBCCCCCBBCBCCBCCCBCBBCB21,4878",
        "repeatCount": 1
    }, {
        "uuid": "E3583050-737C-42E4-BBAB-A56915DEE9A3",
        "name": "Two",
        "frequency": 38109,
        "setsDeviceInput": false,
        "offset": 1,
        "onOffPattern": "171,171,21,64BB21,21CCCCBBBCCCCCBCBCCCCCCBCBBBBB21,1776ABBBCCCCCBBBCCCCCBCBCCCCCCBCBBBBBDABBBCCCCCBBBCCCCCBCBCCCCCCBCBBBBBDABBBCCCCCBBBCCCCCBCBCCCCCCBCBBBBBDABBBCCCCCBBBCCCCCBCBCCCCCCBCBBBBB21,4878",
        "repeatCount": 1
    }, {
        "uuid": "15874555-3795-4841-BB91-67B6753A5C1F",
        "name": "Up",
        "frequency": 38109,
        "setsDeviceInput": false,
        "offset": 1,
        "onOffPattern": "171,171,21,64BB21,21CCCCBBBCCCCCCCCCCBBCBBBBBCCB21,1776ABBBCCCCCBBBCCCCCCCCCCBBCBBBBBCCB21,4878",
        "repeatCount": 1
    }, {
        "uuid": "67A10317-2B6D-441B-A43E-3A5787107D48",
        "name": "Volume Down",
        "frequency": 38109,
        "setsDeviceInput": false,
        "offset": 1,
        "onOffPattern": "171,171,21,64BB21,21CCCCBBBCCCCCBBCBCCCCCCBCBBBB21,1776ABBBCCCCCBBBCCCCCBBCBCCCCCCBCBBBBDABBBCCCCCBBBCCCCCBBCBCCCCCCBCBBBBDABBBCCCCCBBBCCCCCBBCBCCCCCCBCBBBBDABBBCCCCCBBBCCCCCBBCBCCCCCCBCBBBB21,4878",
        "repeatCount": 1
    }, {
        "uuid": "CE51414F-38A4-45D0-B8B9-61B8876DBADA",
        "name": "Volume Up",
        "frequency": 38109,
        "setsDeviceInput": false,
        "offset": 1,
        "onOffPattern": "171,171,21,64BB21,21CCCCBBBCCCCCBBBCCCCCCCCBBBBB21,1776ABBBCCCCCBBBCCCCCBBBCCCCCCCCBBBBBDABBBCCCCCBBBCCCCCBBBCCCCCCCCBBBBBDABBBCCCCCBBBCCCCCBBBCCCCCCCCBBBBB21,4878",
        "repeatCount": 1
    }, {
        "uuid": "A1C46C5E-D94C-4BA7-91D0-2D3750E77A60",
        "name": "Yahoo!",
        "frequency": 38109,
        "setsDeviceInput": false,
        "offset": 1,
        "onOffPattern": "171,171,21,64BB21,21CCCCBBBCCCCCBBCCBCBCCCBBCBCB21,1776ABBBCCCCCBBBCCCCCBBCCBCBCCCBBCBCBDABBBCCCCCBBBCCCCCBBCCBCBCCCBBCBCBDABBBCCCCCBBBCCCCCBBCCBCBCCCBBCBCBDABBBCCCCCBBBCCCCCBBCCBCBCCCBBCBCB21,4878",
        "repeatCount": 1
    }, {
        "uuid": "9A954547-03DC-4303-877F-BC8347F9F860",
        "name": "Zero",
        "frequency": 38109,
        "setsDeviceInput": false,
        "offset": 1,
        "onOffPattern": "171,171,21,64BB21,21CCCCBBBCCCCCBCCCBCCCCBBBCBBB21,1776ABBBCCCCCBBBCCCCCBCCCBCCCCBBBCBBBDABBBCCCCCBBBCCCCCBCCCBCCCCBBBCBBBDABBBCCCCCBBBCCCCCBCCCBCCCCBBBCBBBDABBBCCCCCBBBCCCCCBCCCBCCCCBBBCBBB21,4878",
        "repeatCount": 1
    }]
}]
